Workbook

Sheet admissions
A1: Admission ID | B1: Parent Name | C1: Mobile | D1: Email | E1: Address | F1: City | G1: Student Name | H1: Age | I1: Gender | J1: School | K1: Grade | L1: Level | M1: Batch Code | N1: Mode | O1: Start Date | P1: End Date | Q1: Status | R1: Total Fee | S1: Discount | T1: Manual Adjustment | U1: Adjusted Fee | V1: Total Paid | W1: Pending | X1: Payment Status | Y1: Admission Source | Z1: Referral Type | AA1: Referrer Name | AB1: Created Date | AC1: Send Certificate | AD1: Certificate Status | AE1: Certificate Number | AF1: Certificate Issue Date | AG1: Certificate Sent Date | AH1: Certificate PDF URL | AI1: Certificate Image URL | AJ1: Certificate WhatsApp Status | AK1: Certificate WhatsApp Link | AL1: Certificate WhatsApp Sent Date | AM1: Certificate Error | AN1: Send Receipt | AO1: Receipt Status | AP1: Notification Status
A2: A1001 | B2: Divya Bisen | C2: 7898596308 | D2: bisendivya13@gmail.com | E2: 9a atlas Cosmos spring thane | F2: Thane | G2: Nitivya Katre | H2: 4 | I2: Male | J2: Millenium star kids | K2: Jr kg | L2: Basic | N2: Online | O2: 46091 | P2: 46142 | Q2: Active | R2: 4500 | S2: 0 | T2: 0 | U2: {=IF(R2:R1080="", "", R2:R1080 - IF(S2:S1080="", 0, S2:S1080) + IF(T2:T1080="", 0, T2:T1080))} | V2: =IF(A2="","",SUMIF(payments!B:B,A2,payments!D:D)) | W2: {=IF(U2:U1080="","",U2:U1080-V2:V1080)} | X2: {=IF(U2:U1080="","",IF(V2:V1080=0,"Not Started",IF(V2:V1080<U2:U1080,"Partial","Completed")))} | Y2: Friend Referral | Z2: Friend Referral | AA2: Https://excelkidshub.in/ | AB2: 46096.755
A3: A1002 | B3: Kirti Alkesh Tripathi | C3: 9112307291 | D3: kirti.tripathi0710@gmail.com | E3: Blue villa banglo,lane no 3,Vrindavan colony, kalwad road, opp bird blooming school near goodwill Fabian dhanori | F3: Pune | G3: Vedika Alkesh Tripathi | H3: 4 | I3: Female | J3: Symbiosis international school | K3: Ey-2 | L3: Advanced | N3: Offline | O3: 46091 | P3: 46157 | Q3: Active | R3: 8500 | S3: 0 | T3: 0 | U3: 8500 | V3: =IF(A3="","",SUMIF(payments!B:B,A3,payments!D:D)) | W3: 8500 | X3: Not Started | AA3: Https://excelkidshub.in/ | AB3: 46097.004
A4: A1003 | B4: Rishikesh Kakde | C4: 9359896551 | D4: shrutikakakde29@gmail.com | E4: Flat no.703,B wing, Nivasa uddan society, porwal road,lohegaon pune | F4: Pune | G4: Ridhanya Kakde | H4: 7 | I4: Female | J4: Dr.mar thephillous | K4: 2 | L4: Advanced | N4: Online | O4: 46091 | P4: 46167 | Q4: Active | R4: 0 | S4: 0 | T4: 0 | U4: 0 | V4: =IF(A4="","",SUMIF(payments!B:B,A4,payments!D:D)) | W4: 0 | X4: Not Started | Y4: Social Media | AA4: Https://excelkidshub.in/ | AB4: 46097.405
A5: A1004 | B5: Ranjeeta Limje | C5: 9636169689 | D5: nidhishlimje@gmail.com | E5: EBRO f 304 omaxe riviera Rudarpur | F5: Pune | G5: Yashvi Limje | H5: 5 | I5: Female | J5: Shiny star modern school rudrapur | K5: LKG | L5: Basic | N5: Online | O5: 46091 | P5: 46142 | Q5: Active | R5: 4500 | S5: 0 | T5: 0 | U5: 4500 | V5: =IF(A5="","",SUMIF(payments!B:B,A5,payments!D:D)) | W5: 4500 | X5: Not Started | Y5: Friend Referral | Z5: Friend Referral | AA5: Https://excelkidshub.in/ | AB5: 46098.508
A6: A1005 | B6: Shashikant Pandurang Suryawanshi | C6: 9763401609 | D6: shashi.surya@gmail.com | E6: A1302 Ganga new town, porwal road dhanori pune | F6: Pune | G6: Tanush Shashikant Suryawanshi | H6: 12 | I6: Male | J6: Dr. Martheophilus school | K6: 7 | L6: Advanced | N6: Offline | O6: 46091 | P6: 46157 | Q6: Active | R6: 4500 | S6: 0 | T6: 0 | U6: 4500 | V6: 4500 | W6: 0 | X6: Completed | Y6: Online | AA6: Https://excelkidshub.in/ | AB6: 46102.807
A7: A1006 | B7: Nishant Indapure | C7: 8421111038 | D7: indapureshweta@gmail.com | E7: Nirvana lifecity C Wing Flat no 308 Lohagon | F7: Pune | G7: Nehesh Nishant Indapure | H7: 13 | I7: Male | J7: Pune Internatinal school | K7: 7 | L7: Advanced | N7: Offline | O7: 46091 | P7: 46157 | Q7: Active | R7: 4500 | S7: 0 | T7: 1000 | U7: 5500 | V7: =IF(A7="","",SUMIF(payments!B:B,A7,payments!D:D)) | W7: 5500 | X7: Not Started | Y7: Friend Referral | Z7: Friend Referral | AA7: Https://excelkidshub.in/ | AB7: 46102.984
A8: A1007 | B8: Nishant Indapure | C8: 8421111038 | D8: indapureshweta@gmail.com | E8: Nirvana lifecity Lohagon Pune | F8: Pune | G8: Nehesh Indapure | H8: 13 | I8: Male | J8: Pune Internationl School | K8: 7 | L8: Advanced | M8: Offline L2-B10 Apr'26 | N8: Offline | O8: 46091 | P8: 46157 | Q8: Active | R8: 6500 | S8: 0 | T8: 0 | U8: 6500 | V8: 500 | W8: 6000 | X8: Partial | Y8: Friend Referral | Z8: Friend Referral | AA8: Https://excelkidshub.in/ | AB8: 46103.402
A9: A1008 | B9: Aayesha Jawed Shaikh | C9: 8888810799 | D9: aayesha.shaikh84@gmail.com | E9: Nirman Society,lane 11B, Mumjaba vasti, Dhanori | F9: Pune | G9: Aakib Jawed Shaikh | H9: 8 | I9: Male | J9: Dr. Mar Theophilus School | K9: 3 | L9: Advanced | M9: Offline L3-B9 Apr'26 | N9: Offline | O9: 46091 | P9: 46157 | Q9: Active | R9: 6500 | S9: 0 | T9: 0 | U9: 6500 | V9: 500 | W9: 6000 | X9: Partial | Y9: Friend Referral | Z9: Friend Referral | AA9: Https://excelkidshub.in/ | AB9: 46105.593
A10: A1009 | B10: Kartikkumar Shah | C10: 9998761858 | D10: honeykartikshah1@gmail.com | E10: Bungalow No 72, Lane no 7, Munjabwasti,Dhanori | F10: Pune | G10: Aayanshi Kartikkumar Shah | H10: 5 | I10: Female | J10: Dr Mar Theophilus School | K10: UKG | L10: Basic | M10: Offline L1-B11 Apr'26 | N10: Offline | O10: 46091 | P10: 46142 | Q10: Active | R10: 4500 | S10: 0 | T10: 0 | U10: 4500 | V10: 4500 | W10: 0 | X10: Completed | Y10: Friend Referral | Z10: Friend Referral | AA10: Https://excelkidshub.in/ | AB10: 46105.646 | AN10: Send | AO10: Email Sent
A11: A1010 | B11: Shubha Akshay Kale | C11: 9404303558 | D11: dr.shubhangipachkavde@gmail.com | E11: 29 gold coast society opposite to Atria Munjaba wasti Tingare nagar Dhanori | F11: Pune | G11: Saavi Akshay Kale | H11: 6 | I11: Female | J11: bai najamai nosherwan dastur primary school | K11: 1 | L11: Advanced | M11: Online L2-B8 Apr'26 | N11: Online | O11: 46091 | P11: 46167 | Q11: Active | R11: 6500 | S11: 0 | T11: 0 | U11: 6500 | V11: 6500 | W11: 0 | X11: Completed | Y11: Friend Referral | Z11: Friend Referral | AA11: Https://excelkidshub.in/ | AB11: 46105.962
A12: A1011 | B12: Pragya Sakhare | C12: 9303586081 , 9424980082 | D12: karunasakhare0545@gmail.com | E12: Ward no. 1 himachal nager waraseoni district Balaghat | F12: Pune | G12: Pratyusha Indurkar | H12: 5 | I12: Female | J12: Keshav english school waraseoni district Balaghat mp | K12: UKG | L12: Advanced | M12: Online L2-B8 Apr'26 | N12: Online | O12: 46091 | P12: 46167 | Q12: Active | R12: 6500 | S12: 500 | T12: 0 | U12: 6000 | V12: 6000 | W12: 0 | X12: Completed | Y12: Friend Referral | Z12: Friend Referral | AA12: Https://excelkidshub.in/ | AB12: 46107.007
A13: A1012 | B13: Vishal Vaidya | C13: 9822672693 | D13: vishal.v1988@gmail.com | E13: Ganga Niwas Munjaba wasti Dhanori | F13: Pune | G13: Anika Vaidya | H13: 6 | I13: Female | J13: Erin N nagarwala | K13: 2 | L13: Advanced | N13: Offline | O13: 46091 | P13: 46157 | Q13: Active | R13: 0 | S13: 0 | T13: 0 | U13: 0 | V13: =IF(A13="","",SUMIF(payments!B:B,A13,payments!D:D)) | W13: 0 | X13: Not Started | Y13: Friend Referral | Z13: Friend Referral | AA13: Https://excelkidshub.in/ | AB13: 46111.495
A14: A1013 | B14: Vishal Vaidya | C14: 9822672693 | D14: vishal.v1988@gmail.com | E14: Ganga Niwas Munjaba wasti Dhanori | F14: Pune | G14: Vivaan Vaidya | H14: 9 | I14: Male | J14: KV BEG | K14: 4 | L14: Advanced | N14: Offline | O14: 46091 | P14: 46157 | Q14: Active | R14: 0 | S14: 0 | T14: 0 | U14: 0 | V14: =IF(A14="","",SUMIF(payments!B:B,A14,payments!D:D)) | W14: 0 | X14: Not Started | Y14: Friend Referral | Z14: Friend Referral | AA14: Https://forms.zohopublic.in/excelkidshubzoho1/form/parentenquiryformexcelkidshubphonicsacademy/thankyou/formperma/eoaa5qfag8-0p2dnh5dgzpadjzllhkthogwpbgu7tza | AB14: 46111.497
A15: A1014 | B15: Pranjal Chincholkar | C15: 9373304880 | D15: pranjalchincholkar90@gmail.com | E15: Bhawani Prasad plot no 10, Ramchandra Nagar Lohegaon Khandve Nagar | F15: Pune | G15: Anvi Prasad Chincholkar | H15: 5 | I15: Female | J15: St. Anne's high school | K15: UKG | L15: Basic | N15: Online | O15: 46091 | P15: 46142 | Q15: Active | R15: 0 | S15: 0 | T15: 0 | U15: 0 | V15: =IF(A15="","",SUMIF(payments!B:B,A15,payments!D:D)) | W15: 0 | X15: Not Started | AB15: 46070.775
A16: A1015 | B16: Pranjal Chincholkar | C16: 9595997373 | D16: pranjalchincholkar90@gmail.com | E16: Bhavani Prasad ,plot no.10 lane 4, Ramchandra Nagar Lohegaon Khandve Nagar | F16: Pune | G16: Anvi Prasad Chincholkar | H16: 5 | I16: Female | J16: St Anne's primary school | K16: UKG | L16: Basic | N16: Online | O16: 46091 | P16: 46142 | Q16: Active | R16: 2000 | S16: 0 | T16: 0 | U16: 2000 | V16: =IF(A16="","",SUMIF(payments!B:B,A16,payments!D:D)) | W16: 2000 | X16: Not Started | Y16: From Google search | AB16: 46070.781
A17: A1016 | B17: Sachin Raghunath Kerlekar | C17: 9975440824 | D17: sachin.kerlekar@gmail.com | E17: FN.A21, Castle CHS, Viman Nagar | F17: Pune | G17: Saireesh Sachin Kerlekar | H17: 9 | I17: Male | J17: Narayana Etechno Wagholi | K17: 3 | L17: Basic | N17: Online | O17: 46091 | P17: 46142 | Q17: Active | R17: 6500 | S17: 0 | T17: 0 | U17: 6500 | V17: =IF(A17="","",SUMIF(payments!B:B,A17,payments!D:D)) | W17: 6500 | X17: Not Started | Y17: Friend Referral | Z17: Friend Referral | AB17: 46074.872
A18: A1017 | B18: Sandeep Sharma | C18: 8411009381 | D18: seaya.sharma@gmail.com | E18: Flat 410, Wing F, Gini Belvista, Dhanori | F18: Pune | G18: Seaya Sharma | H18: 4 | I18: Female | J18: VK Patil | K18: LKG | L18: Advanced | N18: Offline | O18: 46091 | P18: 46157 | Q18: Active | R18: 8500 | S18: 0 | T18: 0 | U18: 8500 | V18: =IF(A18="","",SUMIF(payments!B:B,A18,payments!D:D)) | W18: 8500 | X18: Not Started | Y18: Friend Referral | Z18: Friend Referral | AB18: 46076.654
A19: A1018 | B19: Ashish Raghunath Mhasitkar | C19: 9823199271 | D19: ashish.mhasitkar@gmail.com | E19: Mayur Kilbil Society, Dhanori, Pune | F19: Pune | G19: Siddhi Ashish Mhasitkar | H19: 9 | I19: Female | J19: Neuron Labs Dhanori Pune | K19: 3rd | L19: Advanced | N19: Online | O19: 46091 | P19: 46167 | Q19: Active | R19: 6500 | S19: 0 | T19: 0 | U19: 6500 | V19: =IF(A19="","",SUMIF(payments!B:B,A19,payments!D:D)) | W19: 6500 | X19: Not Started | Y19: Friend Referral | Z19: Friend Referral | AB19: 46078.777
A20: A1019 | B20: Ridhima Khera | C20: 9818065684 | D20: riddhmaakhera@gmail.com | E20: E801, satellite towers, Koregaon park , Pune | F20: Pune | G20: Ranveer Kumar | H20: 6 | I20: Male | J20: Billabong international school | K20: 1 | L20: Basic | N20: Online | O20: 46091 | P20: 46142 | Q20: Active | R20: 6500 | S20: 0 | T20: 0 | U20: 6500 | V20: =IF(A20="","",SUMIF(payments!B:B,A20,payments!D:D)) | W20: 6500 | X20: Not Started | Y20: Friend Referral | Z20: Friend Referral | AA20: Https://excelkidshub.in/ | AB20: 46080.716
A21: A1020 | B21: Pratik Gawande | C21: 8087950720 | D21: pratikgd.gawande@gmail.com | E21: 411,Skyways Harmony, Lohegaon | F21: Pune | G21: Nihira Pratik Gawnde | H21: 6 | I21: Female | J21: SSWS | K21: 1 | L21: Basic | N21: Offline | O21: 46091 | P21: 46142 | Q21: Active | R21: 4000 | S21: 0 | T21: 0 | U21: 4000 | V21: =IF(A21="","",SUMIF(payments!B:B,A21,payments!D:D)) | W21: 4000 | X21: Not Started | Y21: Friend Referral | Z21: Friend Referral | AA21: Https://excelkidshub.in/ | AB21: 46082.374
A22: A1021 | B22: Neha Garole | C22: 7507135334 | D22: nehajadhav.22081992@gmail.com | E22: Laxmi nagar dhanori,pune | F22: Pune | G22: Advik Garole | H22: 6 | I22: Male | J22: Mounts and patrick school | K22: Ukg | L22: Advanced | M22: Offline L2-B10 Apr'26 | N22: Offline | O22: 46091 | P22: 46157 | Q22: Active | R22: 6500 | S22: 0 | T22: 0 | U22: 6500 | V22: 3500 | W22: 3000 | X22: Partial | Y22: Friend Referral | Z22: Friend Referral | AA22: Https://excelkidshub.in/ | AB22: 46082.973
A23: A1022 | B23: Basera Waseem Shiledar | C23: 8459403684 | D23: basera.shiledar@gmail.com | E23: Khizra appartment, flat no 301,behind Bharat dhaba,next to ganga aria,dhanori pune | F23: Pune | G23: Zikra Waseem Shiledar | H23: 7 | I23: Female | J23: Nagarwala day school | K23: 1.0 | L23: Advanced | N23: Offline | O23: 46091 | P23: 46157 | Q23: Active | R23: 0 | S23: 0 | T23: 0 | U23: 0 | V23: =IF(A23="","",SUMIF(payments!B:B,A23,payments!D:D)) | W23: 0 | X23: Not Started | AA23: Https://excelkidshub.in/ | AB23: 46082.978
A24: A1023 | B24: Prashant Jadhav | C24: 9623116887 | D24: prshntjdhv707@gmail.com | E24: Jijai building kalwad | F24: Pune | G24: Naitvik Prashant Jadhav | H24: 6 | I24: Male | J24: Asha Vidyalaya | K24: UKG | L24: Basic | N24: Offline | O24: 46091 | P24: 46142 | Q24: Active | R24: 4000 | S24: 0 | T24: 0 | U24: 4000 | V24: =IF(A24="","",SUMIF(payments!B:B,A24,payments!D:D)) | W24: 4000 | X24: Not Started | Y24: Friend Referral | Z24: Friend Referral | AA24: Https://excelkidshub.in/ | AB24: 46083.974
A25: A1024 | B25: Sanjay Pralhad Dandge | C25: 9960732603 | D25: sanjay.dandge1986@gmail.com | E25: Goodwill Nirmiti, B-902, Bharat Mata Road, Lohegaon | F25: Pune | G25: Kaivalya Sanjay Dandge | H25: 8 | I25: Male | J25: Dr. Mar Theophilus School, Dhanori, Pune | K25: 3rd | L25: Advanced | M25: Offline L2-B10 Apr'26 | N25: Offline | O25: 46091 | P25: 46157 | Q25: Active | R25: 6500 | S25: 500 | T25: 0 | U25: 6000 | V25: 6000 | W25: 0 | X25: Completed | Y25: Social Media | AA25: Https://excelkidshub.in/ | AB25: 46085.494
A26: A1025 | B26: Akanksha Saurabh Sharma | C26: 91309901171 | D26: joshiakanksha27@gmail.com | E26: A103 zest county, lohegaon | F26: Pune | G26: Nishtha Sharma | H26: 4 | I26: Female | J26: DYPIS | K26: Jr.Kg | L26: Basic | N26: Offline | O26: 46091 | P26: 46142 | Q26: Active | R26: 4000 | S26: 0 | T26: 0 | U26: 4000 | V26: =IF(A26="","",SUMIF(payments!B:B,A26,payments!D:D)) | W26: 4000 | X26: Not Started | Y26: Google | AA26: Https://excelkidshub.in/ | AB26: 46085.57
A27: A1026 | B27: Dolly Oza | C27: 8087923331 | D27: dollyoza43@gmail.com | E27: Hari om sadan, lane no 4/1 ,sr. No 256/2, Khesepark | F27: Pune | G27: Rhythm Sharma | H27: 5 | I27: Female | J27: Dr. Mar Theophilus School | K27: UKG | L27: Advanced | N27: Online | O27: 46091 | P27: 46167 | Q27: Active | R27: 6000 | S27: 0 | T27: 0 | U27: 6000 | V27: =IF(A27="","",SUMIF(payments!B:B,A27,payments!D:D)) | W27: 6000 | X27: Not Started | Y27: Google | AA27: Https://excelkidshub.in/ | AB27: 46085.665
A28: A1027 | B28: Shilpa Nitin Amgaonkar | C28: 9130824959 | D28: nikhare.shilpa@gmail.com | E28: F703,Gini Belvista DN Parande Park Dhanori Pune | F28: Pune | G28: Shivansh Nitin Amgaonkar | H28: 4 | I28: Male | J28: Vikhe Patil Memorial School | K28: Jr KG | L28: Basic | N28: Offline | O28: 46091 | P28: 46142 | Q28: Active | R28: 4000 | S28: 0 | T28: 0 | U28: 4000 | V28: =IF(A28="","",SUMIF(payments!B:B,A28,payments!D:D)) | W28: 4000 | X28: Not Started | Y28: Friend Referral | Z28: Friend Referral | AA28: Https://excelkidshub.in/ | AB28: 46085.768
A29: A1028 | B29: Radhika Abhijeet Mancharkar | C29: 9763783687 | D29: radhika.narwaria@gmail.com | E29: Flat no 204, Ameya lotus near Brezza society, dhanori road dhanori Pune 411015 | F29: Pune | G29: Virat Abhijeet Mancharkar | H29: 7 | I29: Male | J29: Neuron labs | K29: 2 nd class | L29: Advanced | M29: Online L2-B8 Apr'26 | N29: Online | O29: 46091 | P29: 46167 | Q29: Active | R29: 6500 | S29: 0 | T29: 0 | U29: 6500 | V29: 500 | W29: 6000 | X29: Partial | Y29: Friend Referral | Z29: Friend Referral | AB29: 46085.825
A30: A1029 | B30: Aboli Akshay Kulkarni | C30: 9309768090 | D30: aboliofficial007@gmail.com | E30: C 304 goodwill breeza dhanori | F30: Pune | G30: Aarunya Akshay Kulkarni | H30: 6 | I30: Female | J30: Fun n Fun | K30: UKG | L30: Advanced | N30: Offline | O30: 46091 | P30: 46157 | Q30: Active | R30: 8500 | S30: 0 | T30: 0 | U30: 8500 | V30: =IF(A30="","",SUMIF(payments!B:B,A30,payments!D:D)) | W30: 8500 | X30: Not Started | Y30: Friend Referral | Z30: Friend Referral | AA30: Https://excelkidshub.in/ | AB30: 46085.996
A31: A1030 | B31: Sakina Shaikh | C31: 9850604858 | D31: ssakina0217@gmail.com | E31: C1-302, Goodwill Orchid | F31: Pune | G31: Riana Selvaraj | H31: 7 | I31: Female | J31: The Bishop's | K31: 2 | L31: Advanced | N31: Offline | O31: 46091 | P31: 46157 | Q31: Active | R31: 0 | S31: 0 | T31: 0 | U31: 0 | V31: =IF(A31="","",SUMIF(payments!B:B,A31,payments!D:D)) | W31: 0 | X31: Not Started | Y31: Social Media | AA31: Https://excelkidshub.in/ | AB31: 46086.531
A32: A1031 | B32: Sakina Shaikh | C32: 9850604858 | D32: ssakina0217@gmail.com | E32: C1-302, Goodwill Orchid | F32: Pune | G32: Rian Selvaraj | H32: 7 | I32: Male | J32: The Bishop's | K32: 2 | L32: Advanced | N32: Offline | O32: 46091 | P32: 46157 | Q32: Active | R32: 0 | S32: 0 | T32: 0 | U32: 0 | V32: =IF(A32="","",SUMIF(payments!B:B,A32,payments!D:D)) | W32: 0 | X32: Not Started | Y32: Social Media | AA32: Https://forms.zohopublic.in/excelkidshubzoho1/form/parentenquiryformexcelkidshubphonicsacademy/thankyou/formperma/eoaa5qfag8-0p2dnh5dgzpadjzllhkthogwpbgu7tza | AB32: 46086.532
A33: A1032 | B33: Reema Mishra | C33: 7798814805 | D33: reema.miahra20@gmail.com | E33: Khese park | F33: Pune | G33: Reesha Tiwari | H33: 6 | I33: Female | J33: D Y Patil | K33: Sr kg | L33: Advanced | N33: Online | O33: 46091 | P33: 46167 | Q33: Active | R33: 6000 | S33: 0 | T33: 0 | U33: 6000 | V33: =IF(A33="","",SUMIF(payments!B:B,A33,payments!D:D)) | W33: 6000 | X33: Not Started | Y33: Friend Referral | Z33: Friend Referral | AA33: Https://excelkidshub.in/ | AB33: 46086.536
A34: A1033 | B34: Manali Yavalkar | C34: 8976344256 | D34: manali.yavalkar@gmail.com | E34: A1-1401, Nyati Elysia river front road Kharadi | F34: Pune | G34: Anay Sanket Yavalkar | H34: 7 | I34: Male | J34: Euro school Kharadi | K34: 1 | L34: Advanced | N34: Online | O34: 46091 | P34: 46167 | Q34: Active | R34: 6500 | S34: 0 | T34: 0 | U34: 6500 | V34: =IF(A34="","",SUMIF(payments!B:B,A34,payments!D:D)) | W34: 6500 | X34: Not Started | Y34: Social Media | AA34: Https://excelkidshub.in/ | AB34: 46086.549
A35: A1034 | B35: Dr. Kashmira | C35: 9130028028 | D35: drkashmiralonkar@gmail.com | E35: Ehsaas villa plot no 25 S. No 253/A shivaji Maharaj Road khese park lohegaon Road Pune | F35: Pune | G35: Mannwah Kawale | H35: 6 | I35: Female | J35: DMTS | K35: Ukg | L35: Advanced | M35: Offline L2-B10 Apr'26 | N35: Offline | O35: 46091 | P35: 46157 | Q35: Active | R35: 6500 | S35: 0 | T35: 0 | U35: 6500 | V35: =IF(A35="","",SUMIF(payments!B:B,A35,payments!D:D)) | W35: 6500 | X35: Not Started | Y35: Friend Referral | Z35: Friend Referral | AA35: Https://excelkidshub.in/ | AB35: 46086.956
A36: A1035 | B36: Shruti Sehgal | C36: 9049324573 | D36: shrutisehgal29@gmail.com | E36: B-102 Vivanta Life Vishakha | F36: Pune | G36: Viaan Singh | H36: 6 | I36: Male | J36: Sanskriti | K36: 2.0 | L36: Advanced | N36: Offline | O36: 46091 | P36: 46157 | Q36: Active | R36: 0 | S36: 0 | T36: 0 | U36: 0 | V36: =IF(A36="","",SUMIF(payments!B:B,A36,payments!D:D)) | W36: 0 | X36: Not Started | Y36: Friend Referral | Z36: Friend Referral | AA36: Https://excelkidshub.in/ | AB36: 46088.425
A37: A1036 | B37: Yogendra Uttam Londhe | C37: 9552580236 | D37: saylikamble16@gmail.com | E37: 402,vaman residency sector 21 ghansoli | F37: Pune | G37: Eehita Yogendra Londhe | H37: 6 | I37: Female | J37: DAV airoli | K37: 1.0 | L37: Basic | N37: Online | O37: 46091 | P37: 46142 | Q37: Active | R37: 4500 | S37: 0 | T37: 0 | U37: 4500 | V37: =IF(A37="","",SUMIF(payments!B:B,A37,payments!D:D)) | W37: 4500 | X37: Not Started | Y37: Social Media | AA37: Https://excelkidshub.in/ | AB37: 46088.64
A38: A1037 | B38: Anurag Dattatreya Jagdhane | C38: 9766410479 | D38: snhfstfd@gmail.com | E38: B301 Vivanata life Vishakha | F38: Pune | G38: Amogh Jagdhane | H38: 4 | I38: Male | J38: St Mary's | K38: Nursary | L38: Basic | N38: Offline | O38: 46091 | P38: 46142 | Q38: Active | R38: 4500 | S38: 0 | T38: 0 | U38: 4500 | V38: 4500 | W38: 0 | X38: Completed | Y38: Friend Referral | Z38: Friend Referral | AA38: Https://excelkidshub.in/ | AB38: 46088.69 | AN38: Send | AO38: Not Sent - Payment not completed
A39: A1038 | B39: Anurag Jagdhane | C39: 9766410479 | D39: snhfstfd@gmail.com | E39: B301 Vivanata life Vishakha | F39: Pune | G39: Avni Jagdhane | H39: 5 | I39: Female | J39: St Mary's | K39: LKG | L39: Basic | N39: Offline | O39: 46091 | P39: 46142 | Q39: Active | R39: 6500 | S39: 0 | T39: 0 | U39: 6500 | V39: 6500 | W39: 0 | X39: Completed | Y39: Friend Referral | Z39: Friend Referral | AA39: Https://forms.zohopublic.in/excelkidshubzoho1/form/parentenquiryformexcelkidshubphonicsacademy/thankyou/formperma/eoaa5qfag8-0p2dnh5dgzpadjzllhkthogwpbgu7tza | AB39: 46088.691 | AN39: Send | AO39: Email Sent
A40: A1039 | B40: Sabna | C40: 971558413265 | D40: sabnasivanandan21@gmail.com | E40: Thazhath house anchery thrissur keraala | F40: Pune | G40: Aniketh | H40: 9 | I40: Male | J40: Indian high school | K40: 3.0 | L40: Advanced | N40: Online | O40: 46091 | P40: 46167 | Q40: Active | R40: 6500 | S40: 0 | T40: 0 | U40: 6500 | V40: =IF(A40="","",SUMIF(payments!B:B,A40,payments!D:D)) | W40: 6500 | X40: Not Started | Y40: Social Media | AA40: Https://excelkidshub.in/ | AB40: 46089.047
A41: A1040 | B41: Noopur Deshpande | C41: 8600893449 | D41: noopurdeshpande1010@gmail.com | E41: Tower E flat 1501 Majestic Marbella Downtown Rd Kharadi Pune 411014 | F41: Pune | G41: Adyansh Shukla | H41: 5 | I41: Male | J41: Orchids International | K41: 1.0 | L41: Basic | N41: Online | O41: 46091 | P41: 46142 | Q41: Active | R41: 4500 | S41: 0 | T41: 0 | U41: 4500 | V41: =IF(A41="","",SUMIF(payments!B:B,A41,payments!D:D)) | W41: 4500 | X41: Not Started | Y41: Friend Referral | Z41: Friend Referral | AA41: Https://excelkidshub.in/ | AB41: 46089.582
A42: A1041 | B42: Dipak Gonate | C42: 9096625975 | D42: kbangar9@gmail.com | E42: Flat no 102 A wing star max society Tushar Park Dhanori pune | F42: Pune | G42: Mahir Dipak Gonate | H42: 6 | I42: Male | J42: Akansha fun n fun preschool | K42: UKG | L42: Advanced | N42: Online | O42: 46091 | P42: 46167 | Q42: Active | R42: 6500 | S42: 0 | T42: 0 | U42: 6500 | V42: =IF(A42="","",SUMIF(payments!B:B,A42,payments!D:D)) | W42: 6500 | X42: Not Started | Y42: Friend Referral | Z42: Friend Referral | AA42: Https://excelkidshub.in/ | AB42: 46090.52
A43: A1042 | B43: Nitika Singhal | C43: 7710054522 | D43: nitika.singhal8@gmail.com | E43: Jaypee Kosmos,flat no.1006, KM-29, Sector-134, Noida | F43: Pune | G43: Kiyansh Choudhary | H43: 6 | I43: Male | J43: JBM Global school, Noida, U.P | K43: UKG | L43: Advanced | N43: Online | O43: 46091 | P43: 46167 | Q43: Active | R43: 6500 | S43: 0 | T43: 0 | U43: 6500 | V43: =IF(A43="","",SUMIF(payments!B:B,A43,payments!D:D)) | W43: 6500 | X43: Not Started | Y43: Friend Referral | Z43: Friend Referral | AA43: Https://excelkidshub.in/ | AB43: 46090.572
A44: A1043 | B44: Karishma Salman Attar | C44: 9604561786 | D44: karishmashikalgar7777@gmail.com | E44: Ameer heights, kalwad wasti Lohegaon road,pune | F44: Pune | G44: Zohaib Salman Attar | H44: 5 | I44: Male | J44: Neuron labs | K44: Sr kg | L44: Advanced | M44: Online L2-B8 Apr'26 | N44: Online | O44: 46091 | P44: 46167 | Q44: Active | R44: 6500 | S44: 0 | T44: 0 | U44: 6500 | V44: 3000 | W44: 3500 | X44: Partial | Y44: Social Media | AA44: Https://excelkidshub.in/ | AB44: 46091.03
A45: A1044 | B45: Sachin Dnyaneshwar Bhangare | C45: 9819912114 | D45: bhangresachin@gmail.com | E45: C201, Gini Belvista Society, Dhanori | F45: Pune | G45: Shreesha Sachin Bhangare | H45: 4 | I45: Female | J45: Vikhe Patil Memorial School, Wagholi | K45: Jr. KG | L45: Basic | N45: Online | O45: 46091 | P45: 46142 | Q45: Active | R45: 4000 | S45: 0 | T45: 0 | U45: 4000 | V45: =IF(A45="","",SUMIF(payments!B:B,A45,payments!D:D)) | W45: 4000 | X45: Not Started | Y45: Friend Referral | Z45: Friend Referral | AA45: Https://excelkidshub.in/ | AB45: 46091.484
A46: A1045 | B46: Sanman Shinde | C46: 9552826464 | D46: swara.shinde921@gmail.com | E46: Wadgaon Shinde, Lohegaon, Pune. | F46: Pune | G46: Swaraj Sanman Shinde | H46: 10 | I46: Male | J46: Mount St. Patrick Academy | K46: 5 | L46: Advanced | N46: Offline | O46: 46091 | P46: 46157 | Q46: Active | R46: 8500 | S46: 0 | T46: 0 | U46: 8500 | V46: =IF(A46="","",SUMIF(payments!B:B,A46,payments!D:D)) | W46: 8500 | X46: Not Started | Y46: Friend Referral | Z46: Friend Referral | AA46: Https://excelkidshub.in/ | AB46: 46091.845
A47: A1046 | B47: Krupa Ripal Vadgama | C47: 7990066950 | D47: krupabhardiya@gmail.com | E47: B 201 ambiance antilia,opp euro kids,bavdhan | F47: Pune | G47: Jiyaan Ripal Vadgama | H47: 6 | I47: Male | J47: Sanskriti school | K47: ukg | L47: Basic | N47: Online | O47: 46091 | P47: 46142 | Q47: Active | R47: 4500 | S47: 0 | T47: 0 | U47: 4500 | V47: =IF(A47="","",SUMIF(payments!B:B,A47,payments!D:D)) | W47: 4500 | X47: Not Started | Y47: Friend Referral | Z47: Friend Referral | AA47: Https://excelkidshub.in/ | AB47: 46091.897
A48: A1047 | B48: Neha Akkewar | C48: 9637903044 | D48: shingewar@gmail.com | E48: Flat no.C-1104 Shreewoods society Dhanori | F48: Pune | G48: Maharudra Akkewar | H48: 6 | I48: Male | J48: Neuron labs | K48: currently in Ukg | L48: Advanced | M48: Offline L2-B10 Apr'26 | N48: Offline | O48: 46091 | P48: 46157 | Q48: Active | R48: 6500 | S48: 0 | T48: 0 | U48: 6500 | V48: 500 | W48: 6000 | X48: Partial | Y48: Friend Referral | Z48: Friend Referral | AA48: Https://excelkidshub.in/ | AB48: 46092.663
A49: A1048 | B49: Kartiki Thite | C49: 8805965779 | D49: kartiki.lonkar21@gmail.com | E49: Ambience Antilia Bavdhan | F49: Pune | G49: Siya Thite | H49: 5 | I49: Female | J49: Sanskriti | K49: UKG | L49: Basic | N49: Online | O49: 46091 | P49: 46142 | Q49: Active | R49: 4500 | S49: 0 | T49: 0 | U49: 4500 | V49: =IF(A49="","",SUMIF(payments!B:B,A49,payments!D:D)) | W49: 4500 | X49: Not Started | Y49: Friend Referral | Z49: Friend Referral | AA49: Https://excelkidshub.in/ | AB49: 46092.837
A50: A1049 | B50: Madhuri Morde | C50: 8855966764 | D50: madhurimorde26@gmail.com | E50: Flat no 101, shrey paradise, Siddharth Nagar lane no 1, Dhanori | F50: Pune | G50: Advik Kedar Shirodkar | H50: 5 | I50: Male | J50: Vikhe Patil memorial school | K50: UKG | L50: Advanced | M50: Offline L3-B9 Apr'26 | N50: Offline | O50: 46091 | P50: 46157 | Q50: Active | R50: 6500 | S50: 0 | T50: 0 | U50: 6500 | V50: 3500 | W50: 3000 | X50: Partial | Y50: Poster/Hoarding | AA50: Https://excelkidshub.in/ | AB50: 46094.69
A51: A1050 | B51: Neha Patle | C51: 7693942589 | D51: patleneha79@gmail.com | E51: 1903 samriddhi indralok, bhayandar | F51: Pune | G51: Ridhaan Patle | H51: 6 | I51: Male | J51: Sandipani pre school | K51: Senior Kg | L51: Basic | N51: Online | O51: 46091 | P51: 46142 | Q51: Active | R51: 4000 | S51: 0 | T51: 0 | U51: 4000 | V51: =IF(A51="","",SUMIF(payments!B:B,A51,payments!D:D)) | W51: 4000 | X51: Not Started | Y51: Friend Referral | Z51: Friend Referral | AB51: 46095.481
A52: A1051 | B52: Sophia Edward | C52: 8698078511 | D52: sophy.edward@gmail.com | E52: A 304 ,Phase 5, Tirupati campus, lane no 2,Tingre Nagar Pune 411015 | F52: Pune | G52: Rayanna Rex | H52: 8 | I52: Female | J52: The Bishop's Co Ed school | K52: 3 | L52: Advanced | N52: Online | O52: 46091 | P52: 46167 | Q52: Active | R52: 6500 | S52: 0 | T52: 0 | U52: 6500 | V52: 6500 | W52: 0 | X52: Completed | Y52: Friend Referral | Z52: Friend Referral | AA52: Https://excelkidshub.in/ | AB52: 46095.5
A53: A1052 | B53: Sophia Edward | C53: 8698078511 | D53: sophy.edward@gmail.com | E53: A 304 , Phase 5, Tirupati campus, lane no2, Tingre Nagar, Pune | F53: Pune | G53: Seanna Rex | H53: 8 | I53: Female | J53: The Bishop's Co Ed school | K53: 3 | L53: Advanced | M53: Online L2-B8 Apr'26 | N53: Online | O53: 46091 | P53: 46167 | Q53: Active | R53: 6500 | S53: 0 | T53: 0 | U53: 6500 | V53: 6500 | W53: 0 | X53: Completed | Y53: Friend Referral | Z53: Friend Referral | AA53: Https://forms.zohopublic.in/excelkidshubzoho1/form/parentenquiryformexcelkidshubphonicsacademy/thankyou/formperma/eoaa5qfag8-0p2dnh5dgzpadjzllhkthogwpbgu7tza | AB53: 46095.501
A54: A1053 | B54: Manish Kumar Prasad | C54: 7767983380 | D54: manish0922@gmail.com | E54: Flat No - 204 Wing - D Laxmi Nagar Society Dhanori Pune-411015 | F54: Pune | G54: Saanya Priyadarshini | H54: 6 | I54: Female | J54: Neuron Labs | K54: 1 | L54: Basic | M54: Online L2-B8 Apr'26 | N54: Offline | O54: 46091 | P54: 46142 | Q54: Active | R54: 6500 | S54: 0 | T54: 0 | U54: 6500 | V54: 6500 | W54: 0 | X54: Completed | Y54: Friend Referral | Z54: Friend Referral | AA54: Https://excelkidshub.in/ | AB54: 46095.719
A55: A1054 | B55: Saraswati Suraj Shinde | C55: 9545219922 | D55: shindesarita1985@gmail.com | E55: Flat no 1302-B, Manhattan, Pride world city. Charholi. Pune 412105. | F55: Pune | G55: Advita Suraj Shinde | H55: 5 | I55: Female | J55: Mount St. Patrick Academy | K55: 1 | L55: Basic | N55: Online | O55: 46091 | P55: 46142 | Q55: Active | R55: 4500 | S55: 0 | T55: 0 | U55: 4500 | V55: =IF(A55="","",SUMIF(payments!B:B,A55,payments!D:D)) | W55: 4500 | X55: Not Started | Y55: Friend Referral | Z55: Friend Referral | AA55: Https://excelkidshub.in/ | AB55: 46095.788
A56: A1055 | B56: Ankita nikhil kulkarni | C56: 8591226626 | D56: ankitak1192@gmail.com | E56: A1 502 29gold coast building opp atria society | F56: Pune | G56: Jui nikhil kulkarni | H56: 7 | I56: Female | J56: Pragati international school | K56: 1 | L56: Advanced | N56: Offline | Q56: Active | R56: 8500 | S56: 0 | T56: 0 | U56: 8500 | V56: 8500 | W56: 0 | X56: Completed | Z56: Friend Referral | AB56: 46096.036
A57: A1056 | B57: Ridhima khera | C57: 9818065684 | D57: riddhmaakhera@gmail.com | E57: E801, satellite towers, Koregaon park , Pune | F57: Pune | G57: Ranveer Kumar | H57: 6 | I57: Male | J57: Billabong international school | K57: 1 | L57: Basic | N57: Online | Q57: Active | R57: 4500 | U57: 4500 | V57: 4500 | W57: 0 | X57: Completed | Z57: Friend Referral | AB57: 46080.716
A58: A1057 | B58: Rupesh Dnyaneshwar Tingre | C58: 97675 74555 | D58: pallavi.tingare1988@gmail.com | E58: Sr no 22 near bharat dhaba dhanori pune 411015 | F58: Pune | G58: Paras rupesh tingre | H58: 10 | I58: Male | J58: Bharati vidyapeeth english mediun school | K58: 5 | L58: Advanced | M58: Offline L2-B10 Apr'26 | N58: Offline | Q58: Active | R58: 6500 | U58: 6500 | V58: 500 | W58: 6000 | X58: Partial | AB58: 46113.525
A59: A1058 | B59: Rupesh Dnyaneshwar Tingre | C59: 97675 74555 | D59: pallavi.tingare1988@gmail.com | E59: Sr no 22 near bharat dhaba dhanori pune 411015 | F59: Pune | G59: Paras Rupesh Tingre | H59: 10 | I59: Male | J59: Bharati Vidyapeeth english medium school | K59: 5 | L59: Advanced | N59: Offline | Q59: Active | Z59: Friend Referral | AB59: 46113.527
A60: A1059 | B60: Snehal Gade | C60: 9145570241 | D60: snehal143.gade@gmail.com | E60: Elementto society porwal road lohegoan | F60: Pune | G60: Nirvana p mahadwarkar | H60: 9 | I60: Female | J60: Pune international school | K60: 4 | L60: Advanced | M60: Offline L2-B10 Apr'26 | N60: Offline | Q60: Active | R60: 6500 | U60: 6500 | V60: 6500 | W60: 0 | X60: Completed | Z60: Google | AB60: 46113.604
A61: A1060 | B61: Heena Prakash Raval | C61: 7778959935 | D61: soniheena85@yahoo.com | E61: 8 Siddhivinayak Society R C Technical Road Ghatlodia 380061 Ahmedabad | F61: Pune | G61: Hridaa Prakash Raval | H61: 5 | I61: Female | J61: St Kabir Drive in Road Ahmedabad | K61: Sr kg | L61: Advanced | M61: Online L2-B8 Apr'26 | N61: Online | Q61: Active | R61: 6500 | U61: 6500 | V61: 6500 | W61: 0 | X61: Completed | Z61: Friend Referral | AB61: 46114.694
A62: A1061 | B62: Yogesh Warke | C62: 9607593312 | D62: yogeshwarke5@gmail.com | E62: FLAT NO. 301 BUILDING -A, AAIJI PINK CITY, SATHE WASTI, NEAR HP PETROL PUMP LOHEGAON PUNE.- 411047 | F62: Pune | G62: KARTAVYA YOGESH WARKE | H62: 11 | I62: Male | J62: KALPVRIKSHA ACEDAMY | K62: 6 | L62: Proficient | M62: Offline L3-B9 Apr'26 | N62: Offline | Q62: Active | R62: 6500 | U62: 6500 | V62: 6500 | W62: 0 | X62: Completed | Z62: Friend Referral | AB62: 46115.602
A63: A1062 | B63: Minu Cherian | C63: 9850122307 | D63: jc411047@gmail.com | E63: Revell Orchid society | F63: Pune | G63: Hannah Minu Cherian | H63: 6 | I63: Female | J63: D Y P | K63: 1 | L63: Basic | M63: Offline L1-B11 Apr'26 | N63: Offline | Q63: Active | R63: 4500 | U63: 4500 | V63: 4500 | W63: 0 | X63: Completed | Z63: Friend Referral | AB63: 46117.509 | AN63: Send | AO63: Not Sent - Payment not completed
A64: A1063 | B64: Nidhi | C64: 9412175740 | D64: nidhichaudhary.21@gmail.com | E64: Iftm university | F64: Pune | G64: Tasha | H64: 9 | I64: Female | J64: Jagadguru international School | K64: 5 | L64: Proficient | M64: Offline L3-B9 Apr'26 | N64: Offline | Q64: Active | R64: 6500 | U64: 6500 | V64: 5500 | W64: 1000 | X64: Partial | Z64: Friend Referral | AB64: 46117.669
A65: A1064 | B65: nidhichaudhary | C65: 9412175740 | D65: nidhichaudhary.21@gmail.com | E65: Vivaan park society jakat naka lohegaon | F65: Pune | G65: Gaurik | H65: 6 | I65: Male | J65: Jagadguru international School | K65: 1 | L65: Basic | M65: Offline L1-B11 Apr'26 | N65: Offline | Q65: Active | R65: 4500 | U65: 4500 | V65: 500 | W65: 4000 | X65: Partial | Z65: Friend Referral | AB65: 46117.67
A66: A1065 | B66: Sakina Shaikh | C66: 9850604858 | D66: ssakina0217@gmail.com | E66: Goodwill Orchid C1-302 | F66: Pune | G66: Rian Selvaraj | H66: 7 | I66: Male | J66: The Bishop's | K66: 2 | L66: Advanced | N66: Offline | Q66: Active | R66: 6500 | U66: 6500 | V66: 6500 | W66: 0 | X66: Completed | Z66: Social Media | AB66: 46117.799
A67: A1066 | B67: Sakina Shaikh | C67: 9850604858 | D67: ssakina0217@gmail.com | E67: Goodwill Orchid C1-302 | F67: Pune | G67: Riana Selvaraj | H67: 7 | I67: Female | J67: The Bishop's Co-ed School | K67: 2 | L67: Advanced | M67: Offline L2-B10 Apr'26 | N67: Offline | Q67: Active | R67: 6500 | U67: 6500 | V67: 6500 | W67: 0 | X67: Completed | Z67: Social Media | AB67: 46117.8
A68: A1067 | B68: Bhakti Arun Padule | C68: 9923953578 | D68: bhaktipawar512@gmail.com | E68: C1203 Goodwill breeza society Dhanori | F68: Pune | G68: Arjun Arun Padule | H68: 7 | I68: Male | J68: Jagadguru international | K68: 3 | L68: Advanced | M68: Online L2-B8 Apr'26 | N68: Online | Q68: Active | R68: 6500 | U68: 6500 | V68: 500 | W68: 6000 | X68: Partial | Z68: Friend Referral | AB68: 46117.897
A69: A1068 | B69: Prabhat sharma | C69: 7999597338 | D69: rach3081982@gmail.com | E69: Lukand coloande ch 1 near Datt mandir chowk viman Nagar | F69: Pune | G69: Aarul Sharma | H69: 11 | I69: Female | J69: Ryan international Academy | K69: 6 | L69: Advanced | N69: Online | Q69: Active | Z69: Social Media | AB69: 46119.967
A70: A1069 | B70: Shweta shailesh Dastke | C70: 7447473509 | D70: shweta.dastke@gmail.com | E70: C-607, niwas udaan kutwal colony | F70: Pune | G70: Adinath shailesh Dastke | H70: 7 | I70: Male | J70: Neuron lab | K70: 3 | L70: Proficient | M70: Offline L3-B9 Apr'26 | N70: Offline | Q70: Active | R70: 6500 | U70: 6500 | V70: 500 | W70: 6000 | X70: Partial | Z70: Social Media | AB70: 46120.53
A71: A1070 | G71: Kabir | I71: Male | L71: Advanced | M71: Online L2-B8 Apr'26 | N71: Online | Q71: Active | R71: 6500 | U71: 6500 | V71: 6500 | W71: 0 | X71: Completed | Y71: Admin UI
A72: A1072 | G72: Chitransh | I72: Female | L72: Advanced | M72: Online L2-B8 Apr'26 | N72: Online | Q72: Active | R72: 6500 | U72: 6500 | V72: 6500 | W72: 0 | X72: Completed | Y72: Admin UI
A73: A1073 | G73: Vivaan | I73: Male | L73: Advanced | M73: Offline L3-B9 Apr'26 | N73: Offline | Q73: Active | R73: 6500 | U73: 6500 | V73: 500 | W73: 6000 | X73: Partial
A74: A1074 | G74: Kavita | I74: Female | L74: Proficient | M74: Offline L3-B9 Apr'26 | N74: Offline | Q74: Active | R74: 6500 | U74: 6500 | V74: 500 | W74: 6000 | X74: Partial
A75: A1075 | G75: Aaryan | I75: Male | L75: Proficient | M75: Offline L3-B9 Apr'26 | N75: Offline | Q75: Active | R75: 6500 | U75: 6500 | V75: 500 | W75: 6000 | X75: Partial
A76: A1076 | B76: Vishal Vaidya | C76: 9822672693 | D76: Vishal.v1988@gmail.com | G76: Anika Vaidya | I76: Female | J76: Erin N nagarwala | K76: 2 | L76: Advanced | M76: Offline L2-B10 Apr'26 | N76: Offline | Q76: Active | R76: 6500 | U76: 6500 | V76: 500 | W76: 6000 | X76: Partial | AB76: 46111.495
A77: A1077 | G77: Rayaan | I77: Male | L77: Advanced | M77: Offline L2-B10 Apr'26 | N77: Offline | Q77: Active | R77: 6500 | U77: 6500 | V77: 6500 | W77: 0 | X77: Completed
A78: A1078 | G78: Avani | I78: Female | L78: Advanced | M78: Offline L2-B10 Apr'26 | N78: Offline | Q78: Active | R78: 6500 | U78: 6500 | V78: 6500 | W78: 0 | X78: Completed
A79: A1079 | B79: Praveen | C79: 8055665323 | D79: praveend06@gmail.com | E79: Madhav Nagar, Dhanori | F79: Pune | G79: Shanvika | I79: Female | J79: DYPIS | L79: Basic | N79: Online | Q79: Pending Start | R79: 4500 | S79: 500 | T79: 0 | U79: 4000 | W79: 4000 | X79: Not Started | Y79: Website | AB79: 46122.327 | AP79: Sent
A80: A1080 | B80: Priyanka Yadav | C80: 9452721922 | D80: priyanka.sona2@gmail.com | E80: A203, Revell Orchid Porwal road, Lohegaon | F80: Pune | G80: Anaya Yadav | H80: 6 | I80: Female | J80: GIIS | K80: 2 | L80: Basic | M80: Offline L1-B11 Apr'26 | N80: Offline | Q80: Pending Start | R80: 4500 | S80: 0 | T80: 0 | U80: 4500 | V80: 4500 | W80: 0 | X80: Completed | Y80: Friend Referral | AB80: 46122.39 | AN80: Send | AO80: Email Sent
A81: A1081 | B81: Kavita Agarwal | C81: 9970015476 | D81: kabu.goyal28@gmail.com | E81: B 304, Vivanta life vishakha, Dhanori | F81: Pune | G81: Hinaya Agarwal | H81: 7.5 | I81: Female | J81: Sanskriti school | K81: 3rd | L81: Proficient | M81: Online L3-B12 Apr'26 | N81: Offline | Q81: Pending Start | R81: 6500 | S81: 0 | T81: 0 | U81: 6500 | W81: 6500 | X81: Not Started | Y81: Friend Referral | AB81: 46123.04
A82: A1082 | B82: Ankur Arora | C82: 9990150100 | D82: Ankurarora67@gmail.com | E82: Flat F 701 Goodwill Breeza Dhanori | F82: Pune | G82: Sahaj Arora | H82: 6 | I82: Male | J82: Vibgyor High | K82: 1 | L82: Advanced | M82: Offline L2-B10 Apr'26 | N82: Offline | Q82: Pending Start | R82: 6500 | S82: 0 | T82: 0 | U82: 6500 | V82: 6500 | W82: 0 | X82: Completed | Y82: Website | AB82: 46123.214 | AN82: Send | AO82: Email Sent
A83: A1083 | B83: Archana Yuvraj Ramdas Ghule | C83: 8007266071 | D83: archanaghule92@gmail.com | E83: B2 -404,Ganga Niwas co-operative Hsg Society .lane no-7,Munjawasti, Dhanori, Pune.15 | F83: Pune | G83: Shriyash Yuvraj Ghule | H83: 7 | I83: Male | J83: Erin.N.Nagarwala day school, kalyaninagar | K83: 1 | L83: Advanced | M83: Online L3-B12 Apr'26 | N83: Offline | Q83: Pending Start | R83: 6500 | S83: 0 | T83: 0 | U83: 6500 | V83: 6500 | W83: 0 | X83: Completed | Y83: Friend Referral | AB83: 46125.347 | AN83: Send | AO83: Email Sent
A84: A1084 | B84: Sonali kirtiraj Jadhav | C84: 7719992185 | D84: sonalibhapkar1997@gmail.com | E84: Tirupati kashiganga,dhanori | F84: Pune | G84: Jija kirtiraj Jadhav | H84: 6 | I84: Female | J84: Neuron labs | K84: 1 | L84: Basic | M84: Offline L1-B11 Apr'26 | N84: Offline | Q84: Pending Start | R84: 4500 | S84: 0 | T84: 0 | U84: 4500 | V84: 4500 | W84: 0 | X84: Completed | Y84: Friend Referral | AB84: 46125.959 | AN84: Send | AO84: Email Sent
A85: A1085 | B85: Gajanan Kapate | C85: 9665112029 | D85: drgajanankapate@gmail.com | E85: 103 Tulio Residency Sathe vasti Lohagaon | F85: Pune | G85: Prisha G Kapate | H85: 5 | I85: Female | J85: Hello kids Lohagaon | K85: UKG | L85: Basic | M85: Offline L1-B11 Apr'26 | N85: Offline | Q85: Pending Start | R85: 4500 | S85: 0 | T85: 0 | U85: 4500 | V85: 4500 | W85: 0 | X85: Completed | Y85: Poster/Hoarding | AB85: 46126.041 | AN85: Send | AO85: Email Sent
A86: A1086 | B86: Om Prakash Burma | C86: 9819640695 | D86: om.maheshburma@yahoo.com | E86: E 403, Palladium Plus, Madhav Nagar, Dhanori | F86: Pune | G86: Harshita Burma | H86: 6 | I86: Female | J86: Euro School, Kharadi | K86: 1 | L86: Basic | M86: Offline L1-B11 Apr'26 | N86: Offline | Q86: Pending Start | R86: 4500 | S86: 0 | T86: 0 | U86: 4500 | V86: 4500 | W86: 0 | X86: Completed | Y86: Website | AB86: 46126.049 | AN86: Send | AO86: Email Sent
A87: A1087 | B87: Praveen | C87: 8055665323 | D87: praveend06@gmail.com | E87: Madhav Nagar, Dhanori | F87: Pune | G87: Shanvika | H87: 11 | I87: Female | J87: Dypis | L87: Basic | M87: Offline L1-B11 Apr'26 | N87: Online | Q87: Pending Start | R87: 4500 | S87: 0 | T87: 0 | U87: 4500 | W87: 4500 | X87: Not Started | Y87: Website | AB87: 16/04/2026 21:23:01 | AD87: Sent | AF87: 46136 | AG87: 24/04/2026 10:40:48 | AP87: Sent
A88: A1088 | B88: Ankeeta Patel | C88: 9579130761 | D88: ankeetajaiswal90@gmail.com | E88: J-604, Palladium Grand, Dhanori | F88: Pune | G88: Vaani Patel | H88: 8 | I88: Female | J88: Neuron Labs | K88: 3 | L88: Advanced | N88: Offline | Q88: Pending Start | R88: 6500 | S88: 0 | T88: 0 | U88: 6500 | W88: 6500 | X88: Not Started | Y88: Friend Referral | AB88: 17/04/2026 10:16:59 | AP88: Sent
A89: A1089 | B89: Yogesh Ramnath Shinde | C89: 8329586727 | D89: sheetalumbarkar@rediffmail.com | E89: Flat no.704 ,Shree Hari Vitthal Society,jail Road,Nasik Road | F89: Nasik | G89: Devansh Yogesh Shinde | H89: 7.6 | I89: Male | J89: St. Philomena Convent High School | K89: 2nd | L89: Advanced | M89: Online L2-B8 Apr'26 | N89: Online | Q89: Pending Start | R89: 6500 | S89: 0 | T89: 0 | U89: 6500 | V89: 6500 | W89: 0 | X89: Completed | Y89: Friend Referral | AB89: 21/04/2026 13:11:05 | AN89: Send | AO89: Email Sent | AP89: Sent
A90: A1090 | B90: Pradnya Kulkarni | C90: 9689926978 | D90: pradnyakulkarni12@gmail.com | E90: A 202 Life Square, Porwal road | F90: Pune | G90: Anannya Kulkarni | H90: 9 | I90: Female | J90: Bishops co ed School, Kalyani Nagar | K90: 4 | L90: Advanced | N90: Online | Q90: Pending Start | R90: 6500 | S90: 0 | T90: 0 | U90: 6500 | W90: 6500 | X90: Not Started | Y90: Friend Referral | AB90: 30/04/2026 09:49:00 | AP90: Failed - Failed to send email: You do not have pe
A91: A1091 | B91: Santosh Parab | C91: 9067140931 | D91: Sugandha83.parab@gmail.com | E91: 14/1,Dhanori, pune 411015. | F91: Pune | G91: Riaan Parab | H91: 7 | I91: Male | J91: Dr. Mar Theophilus school | K91: 2 | L91: Proficient | N91: Online | Q91: Pending Start | R91: 6500 | S91: 0 | T91: 0 | U91: 6500 | W91: 6500 | X91: Not Started | Y91: Google | AB91: 46027.432 | AP91: Failed - Failed to send email: You do not have pe
A92: A1092 | B92: Rohit Tambe | C92: 8600233366 | D92: rohit.accord86@gmail.comR | E92: Pride world city , Long Island building J 1104 | F92: Pune | G92: Ved Tambe | H92: 9 | I92: Male | J92: GIIS international school | K92: 4 grade | L92: Proficient | N92: Online | Q92: Pending Start | R92: 6500 | S92: 0 | T92: 0 | U92: 6500 | W92: 6500 | X92: Not Started | Y92: Website | AB92: 46117.435 | AP92: Failed - Failed to send email: You do not have pe
A93: A1093 | B93: Shruti jadhav | C93: 7057405014 | D93: shrutisagar6212@gmail.com | E93: Pimple gurav | F93: Pune | G93: Veer jadhav | H93: 5.5 | I93: Male | J93: Ggis pimpri | K93: 1st | L93: Advanced | N93: Online | Q93: Pending Start | R93: 6500 | S93: 0 | T93: 0 | U93: 6500 | W93: 6500 | X93: Not Started | Y93: Website | AB93: 46117.912 | AP93: Failed - Failed to send email: You do not have pe
A94: A1094 | B94: Sunita babanne/Shivraj babanne | C94: 8600399502 | D94: drsunitagadekar88@gmail.com | E94: D-604 solitaire co-op society | F94: Pune | G94: Jiyansh shivraj babanne | H94: 5 | I94: Male | J94: Dr. Mar Theophilus School | K94: UKG | L94: Basic | N94: Offline | Q94: Pending Start | R94: 4500 | S94: 0 | T94: 0 | U94: 4500 | W94: 4500 | X94: Not Started | Y94: Friend Referral | AB94: 46208.474 | AP94: Failed - Failed to send email: You do not have pe
A95: A1095 | B95: Sunita babanne/ Shivraj babanne | C95: 8600399502 | D95: drsunitagadekar88@gmail.com | E95: D -604 solitaire co op society dhanori | F95: Pune | G95: Jinisha shivraj babanne | H95: 5 | I95: Female | J95: Dr. Mar Theophilus School | K95: UkG | L95: Basic | N95: Offline | Q95: Pending Start | R95: 4500 | S95: 0 | T95: 0 | U95: 4500 | W95: 4500 | X95: Not Started | Y95: Friend Referral | AB95: 46208.476 | AP95: Failed - Failed to send email: You do not have pe
A96: A1096 | B96: Zane Buckridge | C96: 7965223992 | D96: meghan.terry@projectmy.net | E96: 6812 Fadel Divide | F96: North Kacichester | G96: Zane Buckridge | I96: Female | J96: Bedfordshire | K96: applications | L96: Advanced | N96: Offline | Q96: Pending Start | R96: 6500 | S96: 0 | T96: 0 | U96: 6500 | W96: 6500 | X96: Not Started | Y96: Social Media | AB96: 46300.868 | AP96: Failed - Failed to send email: You do not have pe
A97: A1097 | B97: Dr Bhagyashree Gaidhane | C97: 9975198690 | D97: bhagyashreephale@yhaoo.com | E97: D-103 Surbhi Mangalam Apartments Siddharth nagar Dhanori Pune 411015 | F97: Pune | G97: Aarvi Jeevan Gaidhane | H97: 5.6 | I97: Female | J97: St Helena’s school | K97: UKG | L97: Basic | N97: Offline | Q97: Pending Start | R97: 4500 | S97: 0 | T97: 0 | U97: 4500 | W97: 4500 | X97: Not Started | Y97: Friend Referral | AB97: 46331.396 | AP97: Failed - Failed to send email: You do not have pe
A98: A1098 | B98: Ketan Pimple | C98: 9579159496 | D98: ketan.pimple@gmail.com | E98: Pathare Vasti Gharkul Society Lohegaon Pune | F98: Pune | G98: Kriyansh Pimple | H98: 4.5 | I98: Male | J98: Lexicon Kids Viman Nagar | K98: LKG | L98: Basic | N98: Offline | Q98: Pending Start | R98: 4500 | S98: 0 | T98: 0 | U98: 4500 | W98: 4500 | X98: Not Started | Y98: Google | AB98: 46331.826 | AP98: Failed - Failed to send email: You do not have pe
A99: A1099 | B99: Nilesh Baburao Shirke | C99: 9730443644 | D99: nileshshirke47222@gmail.com | E99: Sno 283/2 athvan near shinde tower opposite dominos porwal road lohgaon Pune | F99: Pune | G99: Sanskar Nilesh Shirke | H99: 6 | I99: Male | J99: Bridge blooming school | K99: A | L99: Basic | N99: Offline | Q99: Pending Start | R99: 4500 | S99: 0 | T99: 0 | U99: 4500 | W99: 4500 | X99: Not Started | Y99: Friend Referral | AB99: 21/05/2026 12:52:59 | AP99: Failed - Failed to send email: You do not have pe
A100: A1100 | B100: Sweta Trivedy | C100: 7387414337 | D100: sweta275856@gmail.com | E100: Atlantis city, Porwal Road pune | F100: Pune | G100: Eekja R Trivedy | H100: 4 | I100: Female | J100: Symbiosis | K100: Junior KG | L100: Basic | N100: Offline | Q100: Pending Start | R100: 4500 | S100: 0 | T100: 0 | U100: 4500 | W100: 4500 | X100: Not Started | Y100: Website | AB100: 21/05/2026 16:55:00 | AP100: Failed - Failed to send email: You do not have pe
...

Sheet Teachers_Training

Sheet payments
A1: Payment ID | B1: Admission ID | C1: Payment Date | D1: Amount Paid | E1: Payment Mode | F1: Transaction ID | G1: Notes
A2: PAY001 | B2: A001 | C2: 46097.808 | D2: 4500 | E2: Direct
A3: PAY002 | B3: A002 | C3: 46097.869 | D3: 8500 | E3: Direct | G3: English communication and handwriting
A4: PAY003 | B4: A004 | C4: 46098.794 | D4: 4500 | E4: Direct | G4: Yas
A5: PAY004 | B5: A015 | C5: 46070.931 | D5: 2000 | E5: Direct
A6: PAY005 | B6: A016 | C6: 46090.527 | D6: 6500 | E6: Direct | G6: Looking for his reading and spelling creation improvement
A7: PAY006 | B7: A017 | C7: 46096.001 | D7: 8500 | E7: Direct
A8: PAY007 | B8: A018 | C8: 46089.948 | D8: 6500 | E8: Direct
A9: PAY008 | B9: A019 | C9: 46090.572 | D9: 6500 | E9: Direct
A10: PAY009 | B10: A020 | C10: 46090.962 | D10: 4000 | E10: Direct
A11: PAY010 | B11: A023 | C11: 46090.963 | D11: 4000 | E11: Direct
A12: PAY011 | B12: A025 | C12: 46090.571 | D12: 4000 | E12: Direct
A13: PAY012 | B13: A026 | C13: 46092.773 | D13: 6000 | E13: Direct
A14: PAY013 | B14: A027 | C14: 46093.671 | D14: 4000 | E14: Direct
A15: PAY014 | B15: A029 | C15: 46090.799 | D15: 6500 | E15: Direct
A16: PAY015 | B16: A030 | C16: 46093.671 | D16: 8500 | E16: Direct | G16: Spoken English-basic day to day life useful.
A17: PAY016 | B17: A033 | C17: 46086.563 | D17: 6000 | E17: Direct
A18: PAY017 | B18: A034 | C18: 46090.543 | D18: 6500 | E18: Direct
A19: PAY018 | B19: A037 | C19: 46098.385 | D19: 4500 | E19: Direct
A20: PAY019 | B20: A040 | C20: 46090.383 | D20: 6500 | E20: Direct
A21: PAY020 | B21: A041 | C21: 46097.54 | D21: 4500 | E21: Direct | G21: Please make him speak a lot and pls focus on his pronounciation
A22: PAY021 | B22: A042 | C22: 46090.522 | D22: 6500 | E22: Direct
A23: PAY022 | B23: A043 | C23: 46090.572 | D23: 6500 | E23: Direct
A24: PAY023 | B24: A046 | C24: 46097.556 | D24: 4000 | E24: Direct
A25: PAY024 | B25: A047 | C25: 46111.967 | D25: 8500 | E25: Direct | G25: No such requirements but on daily basis give him homework so that whatever has been taught remains in his mind and give updates of whatever taught in the class so that we can take revision at home.
A26: PAY025 | B26: A048 | C26: 46097.809 | D26: 4500 | E26: Direct
A27: PAY026 | B27: A050 | C27: 46098.437 | D27: 4500 | E27: Direct
A28: PAY027 | B28: A052 | C28: 46094.691 | D28: 8000 | E28: Direct
A29: PAY028 | B29: A053 | C29: 46095.484 | D29: 4000 | E29: Direct
A30: PAY029 | B30: A056 | C30: 46095.86 | D30: 4500 | E30: Direct
A31: PAY030 | B31: A057 | C31: 46095.86 | D31: 4500 | E31: Direct
A32: P001 | B32: A059 | C32: 46121 | D32: 1000 | E32: UPI
A33: P002 | B33: A080 | C33: 46122 | E33: UPI

Sheet batches
A1: Batch Code | B1: Level | C1: Mode | D1: Start Date | E1: End Date | F1: Timing | G1: Capacity | H1: Days | I1: Teacher | J1: Sessions
A2: Online L1-B1 Jan'26 | B2: Basic | C2: Online | D2: 46091 | E2: 46142 | F2: 6:00 PM - 7:00 PM | G2: 12
A3: Offline L1-B2 Feb'26 | B3: Basic | C3: Offline | D3: 46091 | E3: 46142 | F3: 7:30 PM - 8:30 PM | G3: 12
A4: Offline L2-B3 Feb'26 | B4: Advanced | C4: Offline | D4: 46122 | E4: 46173 | F4: 6:00 PM - 7:00 PM | G4: 12
A5: Offline L2-B4 Mar'26 | B5: Advanced | C5: Offline | D5: 46143 | E5: 46174 | F5: 6:00 PM - 7:00 PM | G5: 12
A6: Offline L1-B5 Mar'26 | B6: Basic | C6: Offline | D6: 46091 | E6: 46157 | F6: 5:00 PM - 6:00 PM | G6: 12
A7: Online L2-B6 Mar'26 | B7: Advanced | C7: Online | D7: 46091 | E7: 46167 | F7: 7:30 PM - 8:30 PM | G7: 12
A8: Online L1-B7 Mar'26 | B8: Basic | C8: Online | D8: 46122 | E8: 46168 | F8: 5:00 PM - 6:00 PM | G8: 12
A9: Online L2-B8 Apr'26 | B9: Advanced | C9: Online | D9: 46122 | E9: 46168 | F9: 11:00 AM - 12:00 PM | G9: 12
A10: Offline L3-B9 Apr'26 | B10: Proficient | C10: Offline | D10: 46122 | E10: 46168 | F10: 2:30 PM - 3:30 PM | G10: 12
A11: Offline L2-B10 Apr'26 | B11: Advanced | C11: Offline | D11: 46122 | E11: 46168 | F11: 4:00 PM - 5:00 PM | G11: 12
A12: Offline L1-B11 Apr'26 | B12: Basic | C12: Offline | D12: 46122 | E12: 46168 | F12: 6:00 PM - 7:00 PM | G12: 12
A13: Offline L3-B11 Apr'26 | B13: Proficiant | C13: Online | D13: 46122 | E13: 46168 | F13: 4:00 PM - 5:00 PM | G13: 12
A14: Offline L1-B12 June'26 | B14: Basic | C14: Offline | D14: 46189 | F14: 6:00 PM - 7:00 PM | G14: 12 | H14: Tue/Thu/Sat | J14: 20-24
A15: Online L1-B13 June'26 | B15: Basic | C15: Online | D15: 46189 | F15: 7:30 PM - 8:30 PM | G15: 12 | H15: Tue/Thu/Sat | J15: 20-24
A16: Offline L2-B14 June'26 | B16: Advanced | C16: Offline | D16: 46189 | F16: 6:00 PM - 7:00 PM | G16: 12 | H16: Mon/Wed/Fri | J16: 30-35
A17: Online L2-B15 June'26 | B17: Advanced | C17: Online | D17: 46188 | F17: 7:30 PM - 8:30 PM | G17: 12 | H17: Mon/Wed/Fri | J17: 30-35
A18: Offline Reading June'26 | B18: Reading | C18: Offline | D18: 46188 | F18: 5:00 PM - 6:00 PM | G18: 12 | H18: Mon/Wed/Fri | J18: 30-35
A19: Online Teachers June'26 | B19: Teachers Training | C19: Online | D19: 46182 | F19: 1:00 PM - 3:00 PM | G19: 10 | H19: Mon–Fri | J19: 5

Sheet expenses
A1: Date | B1: Category | C1: Sub Category | D1: Amount | E1: Payment Mode | F1: Notes
A2: 45992 | B2: Printing | C2: Book | D2: 21283 | E2: Online
A3: 45992 | B3: Rent | C3: jan - Dec 2025 | D3: 55200 | E3: Online
A4: 45992 | B4: Marketing | C4: Flex Boad | D4: 5200 | E4: Online
A5: 45992 | B5: Salary | C5: Salary | D5: 16000
A6: 45992 | B6: Salary | C6: Office Boy | D6: 6000
A7: 46037 | B7: Rent | D7: 5000
A8: 46037 | B8: Printing | D8: 1050
A9: 46037 | B9: Salary | C9: salary | D9: 7000
A10: 46037 | B10: Salary | C10: Office Boy | D10: 500
A11: 46063 | B11: Printing | D11: 1865
A12: 46063 | B12: Rent | D12: 5000
A13: 46063 | B13: Salary | D13: 500
A14: 46063 | B14: Salary | D14: 7000
A15: 46083 | B15: Printing | D15: 7650
A16: 46083 | B16: Internet | C16: Website | D16: 3000
A17: 46083 | B17: Salary | D17: 0
A18: 46083 | B18: Events | C18: Chocolate | D18: 1000
A19: 46083 | B19: Miscellanious | C19: Petrol | D19: 1000

Sheet finance-summary
A1: Month | B1: Admission Count | C1: New Admissions Value | D1: Collections This Month | E1: Total Expense | F1: Profit | G1: Closing Pending | H1: Outstanding Admissions | I1: Salary Expense | J1: Marketing Expense | K1: Rent Expense | L1: Software Expense | M1: Other Expense
A2: 2026-01 | C2: =SUMPRODUCT((TEXT(admissions!$AB$2:$AB$78,"yyyy-mm")=$A2)*(admissions!$U$2:$U$78)) | D2: =SUMPRODUCT((TEXT(payments!$C$2:$C$501,"yyyy-mm")=$A2)*(payments!$D$2:$D$501)) | E2: =SUMPRODUCT((TEXT(expenses!$A$2:$A$501,"yyyy-mm")=$A2)*(expenses!$D$2:$D$501)) | F2: =D2-E2 | G2: =SUMPRODUCT((TEXT(admissions!$AB$2:$AB$78,"yyyy-mm")<=$A2)*(admissions!$W$2:$W$78)) | H2: =SUMPRODUCT((admissions!$W$2:$W$78>0)*(TEXT(admissions!$AB$2:$AB$78,"yyyy-mm")<=$A2)) | I2: =SUMPRODUCT((TEXT(expenses!$A$2:$A$501,"yyyy-mm")=$A2)*(expenses!$B$2:$B$501="Salary")*(expenses!$D$2:$D$501)) | J2: =SUMPRODUCT(((TEXT(expenses!$A$2:$A$501,"yyyy-mm")=$A2)*((expenses!$B$2:$B$501="Marketing")+(expenses!$B$2:$B$501="Advertisement")))*(expenses!$D$2:$D$501)) | K2: =SUMPRODUCT((TEXT(expenses!$A$2:$A$501,"yyyy-mm")=$A2)*(expenses!$B$2:$B$501="Rent")*(expenses!$D$2:$D$501)) | L2: =SUMPRODUCT((TEXT(expenses!$A$2:$A$501,"yyyy-mm")=$A2)*(expenses!$B$2:$B$501="Software")*(expenses!$D$2:$D$501)) | M2: =E2-I2-J2-K2-L2
A3: 2026-02 | C3: =SUMPRODUCT((TEXT(admissions!$AB$2:$AB$78,"yyyy-mm")=$A3)*(admissions!$U$2:$U$78)) | D3: =SUMPRODUCT((TEXT(payments!$C$2:$C$501,"yyyy-mm")=$A3)*(payments!$D$2:$D$501)) | E3: =SUMPRODUCT((TEXT(expenses!$A$2:$A$501,"yyyy-mm")=$A3)*(expenses!$D$2:$D$501)) | F3: =D3-E3 | G3: =SUMPRODUCT((TEXT(admissions!$AB$2:$AB$78,"yyyy-mm")<=$A3)*(admissions!$W$2:$W$78)) | H3: =SUMPRODUCT((admissions!$W$2:$W$78>0)*(TEXT(admissions!$AB$2:$AB$78,"yyyy-mm")<=$A3)) | I3: =SUMPRODUCT((TEXT(expenses!$A$2:$A$501,"yyyy-mm")=$A3)*(expenses!$B$2:$B$501="Salary")*(expenses!$D$2:$D$501)) | J3: =SUMPRODUCT(((TEXT(expenses!$A$2:$A$501,"yyyy-mm")=$A3)*((expenses!$B$2:$B$501="Marketing")+(expenses!$B$2:$B$501="Advertisement")))*(expenses!$D$2:$D$501)) | K3: =SUMPRODUCT((TEXT(expenses!$A$2:$A$501,"yyyy-mm")=$A3)*(expenses!$B$2:$B$501="Rent")*(expenses!$D$2:$D$501)) | L3: =SUMPRODUCT((TEXT(expenses!$A$2:$A$501,"yyyy-mm")=$A3)*(expenses!$B$2:$B$501="Software")*(expenses!$D$2:$D$501)) | M3: =E3-I3-J3-K3-L3
A4: 2026-03 | C4: =SUMPRODUCT((TEXT(admissions!$AB$2:$AB$78,"yyyy-mm")=$A4)*(admissions!$U$2:$U$78)) | D4: =SUMPRODUCT((TEXT(payments!$C$2:$C$501,"yyyy-mm")=$A4)*(payments!$D$2:$D$501)) | E4: =SUMPRODUCT((TEXT(expenses!$A$2:$A$501,"yyyy-mm")=$A4)*(expenses!$D$2:$D$501)) | F4: =D4-E4 | G4: =SUMPRODUCT((TEXT(admissions!$AB$2:$AB$78,"yyyy-mm")<=$A4)*(admissions!$W$2:$W$78)) | H4: =SUMPRODUCT((admissions!$W$2:$W$78>0)*(TEXT(admissions!$AB$2:$AB$78,"yyyy-mm")<=$A4)) | I4: =SUMPRODUCT((TEXT(expenses!$A$2:$A$501,"yyyy-mm")=$A4)*(expenses!$B$2:$B$501="Salary")*(expenses!$D$2:$D$501)) | J4: =SUMPRODUCT(((TEXT(expenses!$A$2:$A$501,"yyyy-mm")=$A4)*((expenses!$B$2:$B$501="Marketing")+(expenses!$B$2:$B$501="Advertisement")))*(expenses!$D$2:$D$501)) | K4: =SUMPRODUCT((TEXT(expenses!$A$2:$A$501,"yyyy-mm")=$A4)*(expenses!$B$2:$B$501="Rent")*(expenses!$D$2:$D$501)) | L4: =SUMPRODUCT((TEXT(expenses!$A$2:$A$501,"yyyy-mm")=$A4)*(expenses!$B$2:$B$501="Software")*(expenses!$D$2:$D$501)) | M4: =E4-I4-J4-K4-L4
A5: 2026-04 | C5: =SUMPRODUCT((TEXT(admissions!$AB$2:$AB$78,"yyyy-mm")=$A5)*(admissions!$U$2:$U$78)) | D5: =SUMPRODUCT((TEXT(payments!$C$2:$C$501,"yyyy-mm")=$A5)*(payments!$D$2:$D$501)) | E5: =SUMPRODUCT((TEXT(expenses!$A$2:$A$501,"yyyy-mm")=$A5)*(expenses!$D$2:$D$501)) | F5: =D5-E5 | G5: =SUMPRODUCT((TEXT(admissions!$AB$2:$AB$78,"yyyy-mm")<=$A5)*(admissions!$W$2:$W$78)) | H5: =SUMPRODUCT((admissions!$W$2:$W$78>0)*(TEXT(admissions!$AB$2:$AB$78,"yyyy-mm")<=$A5)) | I5: =SUMPRODUCT((TEXT(expenses!$A$2:$A$501,"yyyy-mm")=$A5)*(expenses!$B$2:$B$501="Salary")*(expenses!$D$2:$D$501)) | J5: =SUMPRODUCT(((TEXT(expenses!$A$2:$A$501,"yyyy-mm")=$A5)*((expenses!$B$2:$B$501="Marketing")+(expenses!$B$2:$B$501="Advertisement")))*(expenses!$D$2:$D$501)) | K5: =SUMPRODUCT((TEXT(expenses!$A$2:$A$501,"yyyy-mm")=$A5)*(expenses!$B$2:$B$501="Rent")*(expenses!$D$2:$D$501)) | L5: =SUMPRODUCT((TEXT(expenses!$A$2:$A$501,"yyyy-mm")=$A5)*(expenses!$B$2:$B$501="Software")*(expenses!$D$2:$D$501)) | M5: =E5-I5-J5-K5-L5
A6: 2026-05 | C6: =SUMPRODUCT((TEXT(admissions!$AB$2:$AB$78,"yyyy-mm")=$A6)*(admissions!$U$2:$U$78)) | D6: =SUMPRODUCT((TEXT(payments!$C$2:$C$501,"yyyy-mm")=$A6)*(payments!$D$2:$D$501)) | E6: =SUMPRODUCT((TEXT(expenses!$A$2:$A$501,"yyyy-mm")=$A6)*(expenses!$D$2:$D$501)) | F6: =D6-E6 | G6: =SUMPRODUCT((TEXT(admissions!$AB$2:$AB$78,"yyyy-mm")<=$A6)*(admissions!$W$2:$W$78)) | H6: =SUMPRODUCT((admissions!$W$2:$W$78>0)*(TEXT(admissions!$AB$2:$AB$78,"yyyy-mm")<=$A6)) | I6: =SUMPRODUCT((TEXT(expenses!$A$2:$A$501,"yyyy-mm")=$A6)*(expenses!$B$2:$B$501="Salary")*(expenses!$D$2:$D$501)) | J6: =SUMPRODUCT(((TEXT(expenses!$A$2:$A$501,"yyyy-mm")=$A6)*((expenses!$B$2:$B$501="Marketing")+(expenses!$B$2:$B$501="Advertisement")))*(expenses!$D$2:$D$501)) | K6: =SUMPRODUCT((TEXT(expenses!$A$2:$A$501,"yyyy-mm")=$A6)*(expenses!$B$2:$B$501="Rent")*(expenses!$D$2:$D$501)) | L6: =SUMPRODUCT((TEXT(expenses!$A$2:$A$501,"yyyy-mm")=$A6)*(expenses!$B$2:$B$501="Software")*(expenses!$D$2:$D$501)) | M6: =E6-I6-J6-K6-L6
A7: 2026-06 | C7: =SUMPRODUCT((TEXT(admissions!$AB$2:$AB$78,"yyyy-mm")=$A7)*(admissions!$U$2:$U$78)) | D7: =SUMPRODUCT((TEXT(payments!$C$2:$C$501,"yyyy-mm")=$A7)*(payments!$D$2:$D$501)) | E7: =SUMPRODUCT((TEXT(expenses!$A$2:$A$501,"yyyy-mm")=$A7)*(expenses!$D$2:$D$501)) | F7: =D7-E7 | G7: =SUMPRODUCT((TEXT(admissions!$AB$2:$AB$78,"yyyy-mm")<=$A7)*(admissions!$W$2:$W$78)) | H7: =SUMPRODUCT((admissions!$W$2:$W$78>0)*(TEXT(admissions!$AB$2:$AB$78,"yyyy-mm")<=$A7)) | I7: =SUMPRODUCT((TEXT(expenses!$A$2:$A$501,"yyyy-mm")=$A7)*(expenses!$B$2:$B$501="Salary")*(expenses!$D$2:$D$501)) | J7: =SUMPRODUCT(((TEXT(expenses!$A$2:$A$501,"yyyy-mm")=$A7)*((expenses!$B$2:$B$501="Marketing")+(expenses!$B$2:$B$501="Advertisement")))*(expenses!$D$2:$D$501)) | K7: =SUMPRODUCT((TEXT(expenses!$A$2:$A$501,"yyyy-mm")=$A7)*(expenses!$B$2:$B$501="Rent")*(expenses!$D$2:$D$501)) | L7: =SUMPRODUCT((TEXT(expenses!$A$2:$A$501,"yyyy-mm")=$A7)*(expenses!$B$2:$B$501="Software")*(expenses!$D$2:$D$501)) | M7: =E7-I7-J7-K7-L7
A8: 2026-07 | C8: =SUMPRODUCT((TEXT(admissions!$AB$2:$AB$78,"yyyy-mm")=$A8)*(admissions!$U$2:$U$78)) | D8: =SUMPRODUCT((TEXT(payments!$C$2:$C$501,"yyyy-mm")=$A8)*(payments!$D$2:$D$501)) | E8: =SUMPRODUCT((TEXT(expenses!$A$2:$A$501,"yyyy-mm")=$A8)*(expenses!$D$2:$D$501)) | F8: =D8-E8 | G8: =SUMPRODUCT((TEXT(admissions!$AB$2:$AB$78,"yyyy-mm")<=$A8)*(admissions!$W$2:$W$78)) | H8: =SUMPRODUCT((admissions!$W$2:$W$78>0)*(TEXT(admissions!$AB$2:$AB$78,"yyyy-mm")<=$A8)) | I8: =SUMPRODUCT((TEXT(expenses!$A$2:$A$501,"yyyy-mm")=$A8)*(expenses!$B$2:$B$501="Salary")*(expenses!$D$2:$D$501)) | J8: =SUMPRODUCT(((TEXT(expenses!$A$2:$A$501,"yyyy-mm")=$A8)*((expenses!$B$2:$B$501="Marketing")+(expenses!$B$2:$B$501="Advertisement")))*(expenses!$D$2:$D$501)) | K8: =SUMPRODUCT((TEXT(expenses!$A$2:$A$501,"yyyy-mm")=$A8)*(expenses!$B$2:$B$501="Rent")*(expenses!$D$2:$D$501)) | L8: =SUMPRODUCT((TEXT(expenses!$A$2:$A$501,"yyyy-mm")=$A8)*(expenses!$B$2:$B$501="Software")*(expenses!$D$2:$D$501)) | M8: =E8-I8-J8-K8-L8
A9: 2026-08 | C9: =SUMPRODUCT((TEXT(admissions!$AB$2:$AB$78,"yyyy-mm")=$A9)*(admissions!$U$2:$U$78)) | D9: =SUMPRODUCT((TEXT(payments!$C$2:$C$501,"yyyy-mm")=$A9)*(payments!$D$2:$D$501)) | E9: =SUMPRODUCT((TEXT(expenses!$A$2:$A$501,"yyyy-mm")=$A9)*(expenses!$D$2:$D$501)) | F9: =D9-E9 | G9: =SUMPRODUCT((TEXT(admissions!$AB$2:$AB$78,"yyyy-mm")<=$A9)*(admissions!$W$2:$W$78)) | H9: =SUMPRODUCT((admissions!$W$2:$W$78>0)*(TEXT(admissions!$AB$2:$AB$78,"yyyy-mm")<=$A9)) | I9: =SUMPRODUCT((TEXT(expenses!$A$2:$A$501,"yyyy-mm")=$A9)*(expenses!$B$2:$B$501="Salary")*(expenses!$D$2:$D$501)) | J9: =SUMPRODUCT(((TEXT(expenses!$A$2:$A$501,"yyyy-mm")=$A9)*((expenses!$B$2:$B$501="Marketing")+(expenses!$B$2:$B$501="Advertisement")))*(expenses!$D$2:$D$501)) | K9: =SUMPRODUCT((TEXT(expenses!$A$2:$A$501,"yyyy-mm")=$A9)*(expenses!$B$2:$B$501="Rent")*(expenses!$D$2:$D$501)) | L9: =SUMPRODUCT((TEXT(expenses!$A$2:$A$501,"yyyy-mm")=$A9)*(expenses!$B$2:$B$501="Software")*(expenses!$D$2:$D$501)) | M9: =E9-I9-J9-K9-L9
A10: 2026-09 | C10: =SUMPRODUCT((TEXT(admissions!$AB$2:$AB$78,"yyyy-mm")=$A10)*(admissions!$U$2:$U$78)) | D10: =SUMPRODUCT((TEXT(payments!$C$2:$C$501,"yyyy-mm")=$A10)*(payments!$D$2:$D$501)) | E10: =SUMPRODUCT((TEXT(expenses!$A$2:$A$501,"yyyy-mm")=$A10)*(expenses!$D$2:$D$501)) | F10: =D10-E10 | G10: =SUMPRODUCT((TEXT(admissions!$AB$2:$AB$78,"yyyy-mm")<=$A10)*(admissions!$W$2:$W$78)) | H10: =SUMPRODUCT((admissions!$W$2:$W$78>0)*(TEXT(admissions!$AB$2:$AB$78,"yyyy-mm")<=$A10)) | I10: =SUMPRODUCT((TEXT(expenses!$A$2:$A$501,"yyyy-mm")=$A10)*(expenses!$B$2:$B$501="Salary")*(expenses!$D$2:$D$501)) | J10: =SUMPRODUCT(((TEXT(expenses!$A$2:$A$501,"yyyy-mm")=$A10)*((expenses!$B$2:$B$501="Marketing")+(expenses!$B$2:$B$501="Advertisement")))*(expenses!$D$2:$D$501)) | K10: =SUMPRODUCT((TEXT(expenses!$A$2:$A$501,"yyyy-mm")=$A10)*(expenses!$B$2:$B$501="Rent")*(expenses!$D$2:$D$501)) | L10: =SUMPRODUCT((TEXT(expenses!$A$2:$A$501,"yyyy-mm")=$A10)*(expenses!$B$2:$B$501="Software")*(expenses!$D$2:$D$501)) | M10: =E10-I10-J10-K10-L10
A11: 2026-10 | C11: =SUMPRODUCT((TEXT(admissions!$AB$2:$AB$78,"yyyy-mm")=$A11)*(admissions!$U$2:$U$78)) | D11: =SUMPRODUCT((TEXT(payments!$C$2:$C$501,"yyyy-mm")=$A11)*(payments!$D$2:$D$501)) | E11: =SUMPRODUCT((TEXT(expenses!$A$2:$A$501,"yyyy-mm")=$A11)*(expenses!$D$2:$D$501)) | F11: =D11-E11 | G11: =SUMPRODUCT((TEXT(admissions!$AB$2:$AB$78,"yyyy-mm")<=$A11)*(admissions!$W$2:$W$78)) | H11: =SUMPRODUCT((admissions!$W$2:$W$78>0)*(TEXT(admissions!$AB$2:$AB$78,"yyyy-mm")<=$A11)) | I11: =SUMPRODUCT((TEXT(expenses!$A$2:$A$501,"yyyy-mm")=$A11)*(expenses!$B$2:$B$501="Salary")*(expenses!$D$2:$D$501)) | J11: =SUMPRODUCT(((TEXT(expenses!$A$2:$A$501,"yyyy-mm")=$A11)*((expenses!$B$2:$B$501="Marketing")+(expenses!$B$2:$B$501="Advertisement")))*(expenses!$D$2:$D$501)) | K11: =SUMPRODUCT((TEXT(expenses!$A$2:$A$501,"yyyy-mm")=$A11)*(expenses!$B$2:$B$501="Rent")*(expenses!$D$2:$D$501)) | L11: =SUMPRODUCT((TEXT(expenses!$A$2:$A$501,"yyyy-mm")=$A11)*(expenses!$B$2:$B$501="Software")*(expenses!$D$2:$D$501)) | M11: =E11-I11-J11-K11-L11
A12: 2026-11 | C12: =SUMPRODUCT((TEXT(admissions!$AB$2:$AB$78,"yyyy-mm")=$A12)*(admissions!$U$2:$U$78)) | D12: =SUMPRODUCT((TEXT(payments!$C$2:$C$501,"yyyy-mm")=$A12)*(payments!$D$2:$D$501)) | E12: =SUMPRODUCT((TEXT(expenses!$A$2:$A$501,"yyyy-mm")=$A12)*(expenses!$D$2:$D$501)) | F12: =D12-E12 | G12: =SUMPRODUCT((TEXT(admissions!$AB$2:$AB$78,"yyyy-mm")<=$A12)*(admissions!$W$2:$W$78)) | H12: =SUMPRODUCT((admissions!$W$2:$W$78>0)*(TEXT(admissions!$AB$2:$AB$78,"yyyy-mm")<=$A12)) | I12: =SUMPRODUCT((TEXT(expenses!$A$2:$A$501,"yyyy-mm")=$A12)*(expenses!$B$2:$B$501="Salary")*(expenses!$D$2:$D$501)) | J12: =SUMPRODUCT(((TEXT(expenses!$A$2:$A$501,"yyyy-mm")=$A12)*((expenses!$B$2:$B$501="Marketing")+(expenses!$B$2:$B$501="Advertisement")))*(expenses!$D$2:$D$501)) | K12: =SUMPRODUCT((TEXT(expenses!$A$2:$A$501,"yyyy-mm")=$A12)*(expenses!$B$2:$B$501="Rent")*(expenses!$D$2:$D$501)) | L12: =SUMPRODUCT((TEXT(expenses!$A$2:$A$501,"yyyy-mm")=$A12)*(expenses!$B$2:$B$501="Software")*(expenses!$D$2:$D$501)) | M12: =E12-I12-J12-K12-L12
A13: 2026-12 | C13: =SUMPRODUCT((TEXT(admissions!$AB$2:$AB$78,"yyyy-mm")=$A13)*(admissions!$U$2:$U$78)) | D13: =SUMPRODUCT((TEXT(payments!$C$2:$C$501,"yyyy-mm")=$A13)*(payments!$D$2:$D$501)) | E13: =SUMPRODUCT((TEXT(expenses!$A$2:$A$501,"yyyy-mm")=$A13)*(expenses!$D$2:$D$501)) | F13: =D13-E13 | G13: =SUMPRODUCT((TEXT(admissions!$AB$2:$AB$78,"yyyy-mm")<=$A13)*(admissions!$W$2:$W$78)) | H13: =SUMPRODUCT((admissions!$W$2:$W$78>0)*(TEXT(admissions!$AB$2:$AB$78,"yyyy-mm")<=$A13)) | I13: =SUMPRODUCT((TEXT(expenses!$A$2:$A$501,"yyyy-mm")=$A13)*(expenses!$B$2:$B$501="Salary")*(expenses!$D$2:$D$501)) | J13: =SUMPRODUCT(((TEXT(expenses!$A$2:$A$501,"yyyy-mm")=$A13)*((expenses!$B$2:$B$501="Marketing")+(expenses!$B$2:$B$501="Advertisement")))*(expenses!$D$2:$D$501)) | K13: =SUMPRODUCT((TEXT(expenses!$A$2:$A$501,"yyyy-mm")=$A13)*(expenses!$B$2:$B$501="Rent")*(expenses!$D$2:$D$501)) | L13: =SUMPRODUCT((TEXT(expenses!$A$2:$A$501,"yyyy-mm")=$A13)*(expenses!$B$2:$B$501="Software")*(expenses!$D$2:$D$501)) | M13: =E13-I13-J13-K13-L13

Sheet batch-dashboard
A1: =IF(batches!A2="","",batches!A2) | G1: =IF(batches!A3="","",batches!A3)
A2: Level / Mode | B2: =IF(A1="","",batches!B2&" / "&batches!C2) | G2: Level / Mode | H2: =IF(G1="","",batches!B3&" / "&batches!C3)
A3: Dates | B3: =IF(A1="","",TEXT(batches!D2,"yyyy-mm-dd")&" to "&TEXT(batches!E2,"yyyy-mm-dd")) | G3: Dates | H3: =IF(G1="","",TEXT(batches!D3,"yyyy-mm-dd")&" to "&TEXT(batches!E3,"yyyy-mm-dd"))
A4: Duration | B4: =IF(OR(batches!D2="",batches!E2=""),"",batches!E2-batches!D2+1&" days") | G4: Duration | H4: =IF(OR(batches!D3="",batches!E3=""),"",batches!E3-batches!D3+1&" days")
A5: Timing | B5: =IF(A1="","",batches!F2) | G5: Timing | H5: =IF(G1="","",batches!F3)
A6: Capacity | B6: =IF(A1="","",batches!G2) | G6: Capacity | H6: =IF(G1="","",batches!G3)
A7: Enrolled | B7: =IF(A1="","",COUNTIF(admissions!$M:$M,batches!A2)) | G7: Enrolled | H7: =IF(G1="","",COUNTIF(admissions!$M:$M,batches!A3))
A8: Available | B8: =IF(OR(batches!A2="",batches!G2=""),"",batches!G2-COUNTIF(admissions!$M:$M,batches!A2)) | G8: Available | H8: =IF(OR(batches!A3="",batches!G3=""),"",batches!G3-COUNTIF(admissions!$M:$M,batches!A3))
A9: Student List | G9: Student List
A10: =IFERROR(__xludf.DUMMYFUNCTION("IF(batches!A2="""","""",TEXTJOIN(CHAR(10),TRUE,FILTER(admissions!$G$2:$G$78,admissions!$M$2:$M$78=batches!A2,"""")))"),"#N/A") | G10: =IFERROR(__xludf.DUMMYFUNCTION("IF(batches!A3="""","""",TEXTJOIN(CHAR(10),TRUE,FILTER(admissions!$G$2:$G$78,admissions!$M$2:$M$78=batches!A3,"""")))"),"#N/A")
A13: =IF(batches!A4="","",batches!A4) | G13: =IF(batches!A5="","",batches!A5)
A14: Level / Mode | B14: =IF(A13="","",batches!B4&" / "&batches!C4) | G14: Level / Mode | H14: =IF(G13="","",batches!B5&" / "&batches!C5)
A15: Dates | B15: =IF(A13="","",TEXT(batches!D4,"yyyy-mm-dd")&" to "&TEXT(batches!E4,"yyyy-mm-dd")) | G15: Dates | H15: =IF(G13="","",TEXT(batches!D5,"yyyy-mm-dd")&" to "&TEXT(batches!E5,"yyyy-mm-dd"))
A16: Duration | B16: =IF(OR(batches!D4="",batches!E4=""),"",batches!E4-batches!D4+1&" days") | G16: Duration | H16: =IF(OR(batches!D5="",batches!E5=""),"",batches!E5-batches!D5+1&" days")
A17: Timing | B17: =IF(A13="","",batches!F4) | G17: Timing | H17: =IF(G13="","",batches!F5)
A18: Capacity | B18: =IF(A13="","",batches!G4) | G18: Capacity | H18: =IF(G13="","",batches!G5)
A19: Enrolled | B19: =IF(A13="","",COUNTIF(admissions!$M:$M,batches!A4)) | G19: Enrolled | H19: =IF(G13="","",COUNTIF(admissions!$M:$M,batches!A5))
A20: Available | B20: =IF(OR(batches!A4="",batches!G4=""),"",batches!G4-COUNTIF(admissions!$M:$M,batches!A4)) | G20: Available | H20: =IF(OR(batches!A5="",batches!G5=""),"",batches!G5-COUNTIF(admissions!$M:$M,batches!A5))
A21: Student List | G21: Student List
A22: =IFERROR(__xludf.DUMMYFUNCTION("IF(batches!A4="""","""",TEXTJOIN(CHAR(10),TRUE,FILTER(admissions!$G$2:$G$78,admissions!$M$2:$M$78=batches!A4,"""")))"),"#N/A") | G22: =IFERROR(__xludf.DUMMYFUNCTION("IF(batches!A5="""","""",TEXTJOIN(CHAR(10),TRUE,FILTER(admissions!$G$2:$G$78,admissions!$M$2:$M$78=batches!A5,"""")))"),"#N/A")
A25: =IF(batches!A6="","",batches!A6) | G25: =IF(batches!A7="","",batches!A7)
A26: Level / Mode | B26: =IF(A25="","",batches!B6&" / "&batches!C6) | G26: Level / Mode | H26: =IF(G25="","",batches!B7&" / "&batches!C7)
A27: Dates | B27: =IF(A25="","",TEXT(batches!D6,"yyyy-mm-dd")&" to "&TEXT(batches!E6,"yyyy-mm-dd")) | G27: Dates | H27: =IF(G25="","",TEXT(batches!D7,"yyyy-mm-dd")&" to "&TEXT(batches!E7,"yyyy-mm-dd"))
A28: Duration | B28: =IF(OR(batches!D6="",batches!E6=""),"",batches!E6-batches!D6+1&" days") | G28: Duration | H28: =IF(OR(batches!D7="",batches!E7=""),"",batches!E7-batches!D7+1&" days")
A29: Timing | B29: =IF(A25="","",batches!F6) | G29: Timing | H29: =IF(G25="","",batches!F7)
A30: Capacity | B30: =IF(A25="","",batches!G6) | G30: Capacity | H30: =IF(G25="","",batches!G7)
A31: Enrolled | B31: =IF(A25="","",COUNTIF(admissions!$M:$M,batches!A6)) | G31: Enrolled | H31: =IF(G25="","",COUNTIF(admissions!$M:$M,batches!A7))
A32: Available | B32: =IF(OR(batches!A6="",batches!G6=""),"",batches!G6-COUNTIF(admissions!$M:$M,batches!A6)) | G32: Available | H32: =IF(OR(batches!A7="",batches!G7=""),"",batches!G7-COUNTIF(admissions!$M:$M,batches!A7))
A33: Student List | G33: Student List
A34: =IFERROR(__xludf.DUMMYFUNCTION("IF(batches!A6="""","""",TEXTJOIN(CHAR(10),TRUE,FILTER(admissions!$G$2:$G$78,admissions!$M$2:$M$78=batches!A6,"""")))"),"#N/A") | G34: =IFERROR(__xludf.DUMMYFUNCTION("IF(batches!A7="""","""",TEXTJOIN(CHAR(10),TRUE,FILTER(admissions!$G$2:$G$78,admissions!$M$2:$M$78=batches!A7,"""")))"),"#N/A")
A37: =IF(batches!A8="","",batches!A8) | G37: =IF(batches!A9="","",batches!A9)
A38: Level / Mode | B38: =IF(A37="","",batches!B8&" / "&batches!C8) | G38: Level / Mode | H38: =IF(G37="","",batches!B9&" / "&batches!C9)
A39: Dates | B39: =IF(A37="","",TEXT(batches!D8,"yyyy-mm-dd")&" to "&TEXT(batches!E8,"yyyy-mm-dd")) | G39: Dates | H39: =IF(G37="","",TEXT(batches!D9,"yyyy-mm-dd")&" to "&TEXT(batches!E9,"yyyy-mm-dd"))
A40: Duration | B40: =IF(OR(batches!D8="",batches!E8=""),"",batches!E8-batches!D8+1&" days") | G40: Duration | H40: =IF(OR(batches!D9="",batches!E9=""),"",batches!E9-batches!D9+1&" days")
A41: Timing | B41: =IF(A37="","",batches!F8) | G41: Timing | H41: =IF(G37="","",batches!F9)
A42: Capacity | B42: =IF(A37="","",batches!G8) | G42: Capacity | H42: =IF(G37="","",batches!G9)
A43: Enrolled | B43: =IF(A37="","",COUNTIF(admissions!$M:$M,batches!A8)) | G43: Enrolled | H43: =IF(G37="","",COUNTIF(admissions!$M:$M,batches!A9))
A44: Available | B44: =IF(OR(batches!A8="",batches!G8=""),"",batches!G8-COUNTIF(admissions!$M:$M,batches!A8)) | G44: Available | H44: =IF(OR(batches!A9="",batches!G9=""),"",batches!G9-COUNTIF(admissions!$M:$M,batches!A9))
A45: Student List | G45: Student List
A46: =IFERROR(__xludf.DUMMYFUNCTION("IF(batches!A8="""","""",TEXTJOIN(CHAR(10),TRUE,FILTER(admissions!$G$2:$G$78,admissions!$M$2:$M$78=batches!A8,"""")))"),"#N/A") | G46: =IFERROR(__xludf.DUMMYFUNCTION("IF(batches!A9="""","""",TEXTJOIN(CHAR(10),TRUE,FILTER(admissions!$G$2:$G$78,admissions!$M$2:$M$78=batches!A9,"""")))"),"#N/A")
A49: =IF(batches!A10="","",batches!A10) | G49: =IF(batches!A11="","",batches!A11)
A50: Level / Mode | B50: =IF(A49="","",batches!B10&" / "&batches!C10) | G50: Level / Mode | H50: =IF(G49="","",batches!B11&" / "&batches!C11)
A51: Dates | B51: =IF(A49="","",TEXT(batches!D10,"yyyy-mm-dd")&" to "&TEXT(batches!E10,"yyyy-mm-dd")) | G51: Dates | H51: =IF(G49="","",TEXT(batches!D11,"yyyy-mm-dd")&" to "&TEXT(batches!E11,"yyyy-mm-dd"))
A52: Duration | B52: =IF(OR(batches!D10="",batches!E10=""),"",batches!E10-batches!D10+1&" days") | G52: Duration | H52: =IF(OR(batches!D11="",batches!E11=""),"",batches!E11-batches!D11+1&" days")
A53: Timing | B53: =IF(A49="","",batches!F10) | G53: Timing | H53: =IF(G49="","",batches!F11)
A54: Capacity | B54: =IF(A49="","",batches!G10) | G54: Capacity | H54: =IF(G49="","",batches!G11)
A55: Enrolled | B55: =IF(A49="","",COUNTIF(admissions!$M:$M,batches!A10)) | G55: Enrolled | H55: =IF(G49="","",COUNTIF(admissions!$M:$M,batches!A11))
A56: Available | B56: =IF(OR(batches!A10="",batches!G10=""),"",batches!G10-COUNTIF(admissions!$M:$M,batches!A10)) | G56: Available | H56: =IF(OR(batches!A11="",batches!G11=""),"",batches!G11-COUNTIF(admissions!$M:$M,batches!A11))
A57: Student List | G57: Student List
A58: =IFERROR(__xludf.DUMMYFUNCTION("IF(batches!A10="""","""",TEXTJOIN(CHAR(10),TRUE,FILTER(admissions!$G$2:$G$78,admissions!$M$2:$M$78=batches!A10,"""")))"),"#N/A") | G58: =IFERROR(__xludf.DUMMYFUNCTION("IF(batches!A11="""","""",TEXTJOIN(CHAR(10),TRUE,FILTER(admissions!$G$2:$G$78,admissions!$M$2:$M$78=batches!A11,"""")))"),"#N/A")
A61: =IF(batches!A12="","",batches!A12) | G61: =IF(admissions!M81="","",admissions!M81)
A62: Level / Mode | B62: =IF(A61="","",batches!B12&" / "&batches!C12) | G62: Level / Mode | H62: =IF(G61="","",batches!B13&" / "&batches!C13)
A63: Dates | B63: =IF(A61="","",TEXT(batches!D12,"yyyy-mm-dd")&" to "&TEXT(batches!E12,"yyyy-mm-dd")) | G63: Dates | H63: =IF(G61="","",TEXT(batches!D13,"yyyy-mm-dd")&" to "&TEXT(batches!E13,"yyyy-mm-dd"))
A64: Duration | B64: =IF(OR(batches!D12="",batches!E12=""),"",batches!E12-batches!D12+1&" days") | G64: Duration | H64: =IF(OR(batches!D13="",batches!E13=""),"",batches!E13-batches!D13+1&" days")
A65: Timing | B65: =IF(A61="","",batches!F12) | G65: Timing | H65: =IF(G61="","",batches!F13)
A66: Capacity | B66: =IF(A61="","",batches!G12) | G66: Capacity | H66: =IF(G61="","",batches!G13)
A67: Enrolled | B67: =IF(A61="","",COUNTIF(admissions!$M:$M,batches!A12)) | G67: Enrolled | H67: =IF(G61="","",COUNTIF(admissions!$M:$M,admissions!M81))
A68: Available | B68: =IF(OR(batches!A12="",batches!G12=""),"",batches!G12-COUNTIF(admissions!$M:$M,batches!A12)) | G68: Available | H68: =IF(OR(admissions!M81="",batches!G13=""),"",batches!G13-COUNTIF(admissions!$M:$M,admissions!M81))
A69: Student List | G69: Student List
A70: =IFERROR(__xludf.DUMMYFUNCTION("IF(batches!A12="""","""",TEXTJOIN(CHAR(10),TRUE,FILTER(admissions!$G$2:$G$78,admissions!$M$2:$M$78=batches!A12,"""")))"),"#N/A") | G70: =IFERROR(__xludf.DUMMYFUNCTION("IF(admissions!M81="""","""",TEXTJOIN(CHAR(10),TRUE,FILTER(admissions!$G$2:$G$78,admissions!$M$2:$M$78=admissions!M81,"""")))"),"#N/A")
A73: =IF(batches!A14="","",batches!A14) | G73: =IF(batches!A15="","",batches!A15)
A74: Level / Mode | B74: =IF(A73="","",batches!B14&" / "&batches!C14) | G74: Level / Mode | H74: =IF(G73="","",batches!B15&" / "&batches!C15)
A75: Dates | B75: =IF(A73="","",TEXT(batches!D14,"yyyy-mm-dd")&" to "&TEXT(batches!E14,"yyyy-mm-dd")) | G75: Dates | H75: =IF(G73="","",TEXT(batches!D15,"yyyy-mm-dd")&" to "&TEXT(batches!E15,"yyyy-mm-dd"))
A76: Duration | B76: =IF(OR(batches!D14="",batches!E14=""),"",batches!E14-batches!D14+1&" days") | G76: Duration | H76: =IF(OR(batches!D15="",batches!E15=""),"",batches!E15-batches!D15+1&" days")
A77: Timing | B77: =IF(A73="","",#REF!) | G77: Timing | H77: =IF(G73="","",batches!F14)
A78: Capacity | B78: =IF(A73="","",batches!G14) | G78: Capacity | H78: =IF(G73="","",batches!G15)
A79: Enrolled | B79: =IF(A73="","",COUNTIF(admissions!$M:$M,batches!A14)) | G79: Enrolled | H79: =IF(G73="","",COUNTIF(admissions!$M:$M,batches!A15))
A80: Available | B80: =IF(OR(batches!A14="",batches!G14=""),"",batches!G14-COUNTIF(admissions!$M:$M,batches!A14)) | G80: Available | H80: =IF(OR(batches!A15="",batches!G15=""),"",batches!G15-COUNTIF(admissions!$M:$M,batches!A15))
A81: Student List | G81: Student List
A82: =IFERROR(__xludf.DUMMYFUNCTION("IF(batches!A14="""","""",TEXTJOIN(CHAR(10),TRUE,FILTER(admissions!$G$2:$G$78,admissions!$M$2:$M$78=batches!A14,"""")))"),"#N/A") | G82: =IFERROR(__xludf.DUMMYFUNCTION("IF(batches!A15="""","""",TEXTJOIN(CHAR(10),TRUE,FILTER(admissions!$G$2:$G$78,admissions!$M$2:$M$78=batches!A15,"""")))"),"#N/A")
A85: =IF(batches!A16="","",batches!A16) | G85: =IF(batches!A17="","",batches!A17)
A86: Level / Mode | B86: =IF(A85="","",batches!B16&" / "&batches!C16) | G86: Level / Mode | H86: =IF(G85="","",batches!B17&" / "&batches!C17)
A87: Dates | B87: =IF(A85="","",TEXT(batches!D16,"yyyy-mm-dd")&" to "&TEXT(batches!E16,"yyyy-mm-dd")) | G87: Dates | H87: =IF(G85="","",TEXT(batches!D17,"yyyy-mm-dd")&" to "&TEXT(batches!E17,"yyyy-mm-dd"))
A88: Duration | B88: =IF(OR(batches!D16="",batches!E16=""),"",batches!E16-batches!D16+1&" days") | G88: Duration | H88: =IF(OR(batches!D17="",batches!E17=""),"",batches!E17-batches!D17+1&" days")
A89: Timing | B89: =IF(A85="","",batches!F15) | G89: Timing | H89: =IF(G85="","",batches!F16)
A90: Capacity | B90: =IF(A85="","",batches!G16) | G90: Capacity | H90: =IF(G85="","",batches!G17)
A91: Enrolled | B91: =IF(A85="","",COUNTIF(admissions!$M:$M,batches!A16)) | G91: Enrolled | H91: =IF(G85="","",COUNTIF(admissions!$M:$M,batches!A17))
A92: Available | B92: =IF(OR(batches!A16="",batches!G16=""),"",batches!G16-COUNTIF(admissions!$M:$M,batches!A16)) | G92: Available | H92: =IF(OR(batches!A17="",batches!G17=""),"",batches!G17-COUNTIF(admissions!$M:$M,batches!A17))
A93: Student List | G93: Student List
A94: =IFERROR(__xludf.DUMMYFUNCTION("IF(batches!A16="""","""",TEXTJOIN(CHAR(10),TRUE,FILTER(admissions!$G$2:$G$78,admissions!$M$2:$M$78=batches!A16,"""")))"),"#N/A") | G94: =IFERROR(__xludf.DUMMYFUNCTION("IF(batches!A17="""","""",TEXTJOIN(CHAR(10),TRUE,FILTER(admissions!$G$2:$G$78,admissions!$M$2:$M$78=batches!A17,"""")))"),"#N/A")
A97: =IF(batches!A18="","",batches!A18) | G97: =IF(batches!A19="","",batches!A19)
A98: Level / Mode | B98: =IF(A97="","",batches!B18&" / "&batches!C18) | G98: Level / Mode | H98: =IF(G97="","",batches!B19&" / "&batches!C19)
A99: Dates | B99: =IF(A97="","",TEXT(batches!D18,"yyyy-mm-dd")&" to "&TEXT(batches!E18,"yyyy-mm-dd")) | G99: Dates | H99: =IF(G97="","",TEXT(batches!D19,"yyyy-mm-dd")&" to "&TEXT(batches!E19,"yyyy-mm-dd"))
A100: Duration | B100: =IF(OR(batches!D18="",batches!E18=""),"",batches!E18-batches!D18+1&" days") | G100: Duration | H100: =IF(OR(batches!D19="",batches!E19=""),"",batches!E19-batches!D19+1&" days")
A101: Timing | B101: =IF(A97="","",batches!F17) | G101: Timing | H101: =IF(G97="","",batches!F19)
A102: Capacity | B102: =IF(A97="","",#REF!) | G102: Capacity | H102: =IF(G97="","",batches!G19)
A103: Enrolled | B103: =IF(A97="","",COUNTIF(admissions!$M:$M,batches!A18)) | G103: Enrolled | H103: =IF(G97="","",COUNTIF(admissions!$M:$M,batches!A19))
A104: Available | B104: =IF(OR(batches!A18="",#REF!=""),"",#REF!-COUNTIF(admissions!$M:$M,batches!A18)) | G104: Available | H104: =IF(OR(batches!A19="",batches!G19=""),"",batches!G19-COUNTIF(admissions!$M:$M,batches!A19))
A105: Student List | G105: Student List
A106: =IFERROR(__xludf.DUMMYFUNCTION("IF(batches!A18="""","""",TEXTJOIN(CHAR(10),TRUE,FILTER(admissions!$G$2:$G$78,admissions!$M$2:$M$78=batches!A18,"""")))"),"#N/A") | G106: =IFERROR(__xludf.DUMMYFUNCTION("IF(batches!A19="""","""",TEXTJOIN(CHAR(10),TRUE,FILTER(admissions!$G$2:$G$78,admissions!$M$2:$M$78=batches!A19,"""")))"),"#N/A")
A109: =IF(batches!A20="","",batches!A20) | G109: =IF(batches!A21="","",batches!A21)
A110: Level / Mode | B110: =IF(A109="","",batches!B20&" / "&batches!C20) | G110: Level / Mode | H110: =IF(G109="","",batches!B21&" / "&batches!C21)
A111: Dates | B111: =IF(A109="","",TEXT(batches!D20,"yyyy-mm-dd")&" to "&TEXT(batches!E20,"yyyy-mm-dd")) | G111: Dates | H111: =IF(G109="","",TEXT(batches!D21,"yyyy-mm-dd")&" to "&TEXT(batches!E21,"yyyy-mm-dd"))
A112: Duration | B112: =IF(OR(batches!D20="",batches!E20=""),"",batches!E20-batches!D20+1&" days") | G112: Duration | H112: =IF(OR(batches!D21="",batches!E21=""),"",batches!E21-batches!D21+1&" days")
A113: Timing | B113: =IF(A109="","",batches!F20) | G113: Timing | H113: =IF(G109="","",batches!F21)
A114: Capacity | B114: =IF(A109="","",batches!G20) | G114: Capacity | H114: =IF(G109="","",batches!G21)
A115: Enrolled | B115: =IF(A109="","",COUNTIF(admissions!$M:$M,batches!A20)) | G115: Enrolled | H115: =IF(G109="","",COUNTIF(admissions!$M:$M,batches!A21))
A116: Available | B116: =IF(OR(batches!A20="",batches!G20=""),"",batches!G20-COUNTIF(admissions!$M:$M,batches!A20)) | G116: Available | H116: =IF(OR(batches!A21="",batches!G21=""),"",batches!G21-COUNTIF(admissions!$M:$M,batches!A21))
A117: Student List | G117: Student List
A118: =IFERROR(__xludf.DUMMYFUNCTION("IF(batches!A20="""","""",TEXTJOIN(CHAR(10),TRUE,FILTER(admissions!$G$2:$G$78,admissions!$M$2:$M$78=batches!A20,"""")))"),"") | G118: =IFERROR(__xludf.DUMMYFUNCTION("IF(batches!A21="""","""",TEXTJOIN(CHAR(10),TRUE,FILTER(admissions!$G$2:$G$78,admissions!$M$2:$M$78=batches!A21,"""")))"),"")
...

Sheet admission_queue
A1: Timestamp | B1: Payload | C1: Status
